{"version":"1.12.0","metadata":{"app":"mastodon","language":{"name":"ruby","engine":"ruby","version":"3.2.2"},"client":{"name":"appmap","url":"https://github.com/applandinc/appmap-ruby","version":"0.102.1"},"frameworks":[{"name":"rails","version":"7.1.1"},{"name":"rspec","version":"3.12.2"}],"git":{"repository":"https://github.com/sgrigson/mastodon.git","branch":"appmap-config","commit":"2c1ae2317e8741caf25b51e9b3b2c15776c54ae3","status":["M .husky/pre-commit"],"git_last_annotated_tag":"0.1.2-14608-g2c1ae2317e8741caf25b51e9b3b2c15776c54ae3","git_last_tag":"v4.2.0","git_commits_since_last_annotated_tag":0,"git_commits_since_last_tag":0},"name":"Mastodon::CLI::Accounts #prune does not prune local accounts","source_location":"spec/lib/mastodon/cli/accounts_spec.rb","recorder":{"name":"rspec","type":"tests"},"test_status":"succeeded"},"classMap":[{"name":"lib/mastodon/cli","type":"package","children":[{"name":"Mastodon","type":"class","children":[{"name":"CLI","type":"class","children":[{"name":"Accounts","type":"class","children":[{"name":"prune","type":"function","location":"lib/mastodon/cli/accounts.rb:556","static":false}]}]}]}]},{"name":"app","type":"package","children":[{"name":"models","type":"package","children":[{"name":"Account","type":"class","children":[{"name":"bot?","type":"function","location":"app/models/account.rb:171","static":false},{"name":"group?","type":"function","location":"app/models/account.rb:185","static":false},{"name":"suspended?","type":"function","location":"app/models/account.rb:237","static":false},{"name":"silenced?","type":"function","location":"app/models/account.rb:225","static":false}]},{"name":"concerns","type":"package","children":[{"name":"Redisable","type":"class","children":[{"name":"redis","type":"function","location":"app/models/concerns/redisable.rb:4","static":false}]}]}]},{"name":"lib","type":"package","children":[{"name":"RequestPool","type":"class","children":[{"name":"flush","type":"function","location":"app/lib/request_pool.rb:114","static":false}]},{"name":"connection_pool","type":"package","children":[{"name":"ConnectionPool","type":"class","children":[{"name":"SharedConnectionPool","type":"class","children":[{"name":"flush","type":"function","location":"app/lib/connection_pool/shared_connection_pool.rb:13","static":false}]},{"name":"SharedTimedStack","type":"class","children":[{"name":"flush","type":"function","location":"app/lib/connection_pool/shared_timed_stack.rb:51","static":false}]}]}]},{"name":"FeedManager","type":"class","children":[{"name":"clean_feeds!","type":"function","location":"app/lib/feed_manager.rb:294","static":false},{"name":"key","type":"function","location":"app/lib/feed_manager.rb:29","static":false}]}]}]},{"name":"activesupport","type":"package","children":[{"name":"ActiveSupport","type":"class","children":[{"name":"Callbacks","type":"class","children":[{"name":"CallbackSequence","type":"class","children":[{"name":"invoke_before","type":"function","location":"vendor/bundle/ruby/3.2.0/gems/activesupport-7.1.1/lib/active_support/callbacks.rb:597","static":false,"labels":["mvc.before_action"]},{"name":"invoke_after","type":"function","location":"vendor/bundle/ruby/3.2.0/gems/activesupport-7.1.1/lib/active_support/callbacks.rb:601","static":false,"labels":["mvc.after_action"]}]}]}]}]}],"events":[{"id":2854066,"event":"call","thread_id":9160,"defined_class":"Mastodon::CLI::Accounts","method_id":"prune","path":"lib/mastodon/cli/accounts.rb","lineno":556,"static":false,"parameters":[],"receiver":{"class":"Mastodon::CLI::Accounts","object_id":13980700,"value":"#<Mastodon::CLI::Accounts:0x00007fc8e13d37c0>"}},{"id":2854067,"event":"call","thread_id":9160,"sql_query":{"sql":"SELECT \"accounts\".\"id\", \"accounts\".\"username\", \"accounts\".\"domain\", \"accounts\".\"private_key\", \"accounts\".\"public_key\", \"accounts\".\"created_at\", \"accounts\".\"updated_at\", \"accounts\".\"note\", \"accounts\".\"display_name\", \"accounts\".\"uri\", \"accounts\".\"url\", \"accounts\".\"avatar_file_name\", \"accounts\".\"avatar_content_type\", \"accounts\".\"avatar_file_size\", \"accounts\".\"avatar_updated_at\", \"accounts\".\"header_file_name\", \"accounts\".\"header_content_type\", \"accounts\".\"header_file_size\", \"accounts\".\"header_updated_at\", \"accounts\".\"avatar_remote_url\", \"accounts\".\"locked\", \"accounts\".\"header_remote_url\", \"accounts\".\"last_webfingered_at\", \"accounts\".\"inbox_url\", \"accounts\".\"outbox_url\", \"accounts\".\"shared_inbox_url\", \"accounts\".\"followers_url\", \"accounts\".\"protocol\", \"accounts\".\"memorial\", \"accounts\".\"moved_to_account_id\", \"accounts\".\"featured_collection_url\", \"accounts\".\"fields\", \"accounts\".\"actor_type\", \"accounts\".\"discoverable\", \"accounts\".\"also_known_as\", \"accounts\".\"silenced_at\", \"accounts\".\"suspended_at\", \"accounts\".\"hide_collections\", \"accounts\".\"avatar_storage_schema_version\", \"accounts\".\"header_storage_schema_version\", \"accounts\".\"devices_url\", \"accounts\".\"suspension_origin\", \"accounts\".\"sensitized_at\", \"accounts\".\"trendable\", \"accounts\".\"reviewed_at\", \"accounts\".\"requested_review_at\", \"accounts\".\"indexable\" FROM \"accounts\" WHERE \"accounts\".\"domain\" IS NOT NULL AND \"accounts\".\"actor_type\" NOT IN ($1, $2) AND (NOT EXISTS (SELECT 1 FROM mentions WHERE account_id = accounts.id)) AND (NOT EXISTS (SELECT 1 FROM favourites WHERE account_id = accounts.id)) AND (NOT EXISTS (SELECT 1 FROM statuses WHERE account_id = accounts.id)) AND (NOT EXISTS (SELECT 1 FROM follows WHERE account_id = accounts.id OR target_account_id = accounts.id)) AND (NOT EXISTS (SELECT 1 FROM blocks WHERE account_id = accounts.id OR target_account_id = accounts.id)) AND (NOT EXISTS (SELECT 1 FROM mutes WHERE target_account_id = accounts.id)) AND (NOT EXISTS (SELECT 1 FROM reports WHERE target_account_id = accounts.id)) AND (NOT EXISTS (SELECT 1 FROM follow_requests WHERE account_id = accounts.id OR target_account_id = accounts.id)) ORDER BY \"accounts\".\"id\" ASC LIMIT $3","database_type":"postgres"}},{"id":2854068,"event":"return","thread_id":9160,"parent_id":2854067,"elapsed":0.006099749,"elapsed_instrumentation":0.00012227700790390372},{"id":2854069,"event":"call","thread_id":9160,"defined_class":"Account","method_id":"bot","path":"app/models/account.rb","lineno":171,"static":false,"parameters":[],"receiver":{"class":"Account","object_id":13980740,"value":"#<Account:0x00007fc8e21d2948>"}},{"id":2854070,"event":"return","thread_id":9160,"parent_id":2854069,"elapsed":2.560298889875412e-05,"elapsed_instrumentation":0.0001475409953854978},{"id":2854071,"event":"call","thread_id":9160,"defined_class":"Account","method_id":"group","path":"app/models/account.rb","lineno":185,"static":false,"parameters":[],"receiver":{"class":"Account","object_id":13980740,"value":"#<Account:0x00007fc8e21d2948>"}},{"id":2854072,"event":"return","thread_id":9160,"parent_id":2854071,"elapsed":5.7470169849693775e-06,"elapsed_instrumentation":8.374598110094666e-05,"return_value":{"class":"TrueClass","value":"true","object_id":20}},{"id":2854073,"event":"call","thread_id":9160,"defined_class":"Account","method_id":"bot","path":"app/models/account.rb","lineno":171,"static":false,"parameters":[],"receiver":{"class":"Account","object_id":13980760,"value":"#<Account:0x00007fc8e21d2808>"}},{"id":2854074,"event":"return","thread_id":9160,"parent_id":2854073,"elapsed":9.29197994992137e-06,"elapsed_instrumentation":6.242498056963086e-05},{"id":2854075,"event":"call","thread_id":9160,"defined_class":"Account","method_id":"group","path":"app/models/account.rb","lineno":185,"static":false,"parameters":[],"receiver":{"class":"Account","object_id":13980760,"value":"#<Account:0x00007fc8e21d2808>"}},{"id":2854076,"event":"return","thread_id":9160,"parent_id":2854075,"elapsed":4.215980879962444e-06,"elapsed_instrumentation":5.313701694831252e-05},{"id":2854077,"event":"call","thread_id":9160,"defined_class":"Account","method_id":"suspended?","path":"app/models/account.rb","lineno":237,"static":false,"parameters":[],"receiver":{"class":"Account","object_id":13980760,"value":"#<Account:0x00007fc8e21d2808>"}},{"id":2854078,"event":"return","thread_id":9160,"parent_id":2854077,"elapsed":3.280199598520994e-05,"elapsed_instrumentation":0.0002990820212289691},{"id":2854079,"event":"call","thread_id":9160,"defined_class":"Account","method_id":"silenced?","path":"app/models/account.rb","lineno":225,"static":false,"parameters":[],"receiver":{"class":"Account","object_id":13980760,"value":"#<Account:0x00007fc8e21d2808>"}},{"id":2854080,"event":"return","thread_id":9160,"parent_id":2854079,"elapsed":1.214898657053709e-05,"elapsed_instrumentation":6.501603638753295e-05},{"id":2854081,"event":"call","thread_id":9160,"defined_class":"ActiveSupport::Callbacks::CallbackSequence","method_id":"invoke_before","path":"vendor/bundle/ruby/3.2.0/gems/activesupport-7.1.1/lib/active_support/callbacks.rb","lineno":597,"static":false,"parameters":[{"name":"arg","class":"ActiveSupport::Callbacks::Filters::Environment","object_id":13980780,"value":null,"kind":"req"}],"receiver":{"class":"ActiveSupport::Callbacks::CallbackSequence","object_id":5268680,"value":"#<ActiveSupport::Callbacks::CallbackSequence:0x00007fc930d01c30>"}},{"id":2854082,"event":"call","thread_id":9160,"sql_query":{"sql":"SAVEPOINT active_record_1","database_type":"postgres"}},{"id":2854083,"event":"return","thread_id":9160,"parent_id":2854082,"elapsed":0.00090629,"elapsed_instrumentation":9.556498844176531e-05},{"id":2854084,"event":"call","thread_id":9160,"sql_query":{"sql":"SELECT \"users\".\"id\", \"users\".\"email\", \"users\".\"created_at\", \"users\".\"updated_at\", \"users\".\"encrypted_password\", \"users\".\"reset_password_token\", \"users\".\"reset_password_sent_at\", \"users\".\"sign_in_count\", \"users\".\"current_sign_in_at\", \"users\".\"last_sign_in_at\", \"users\".\"admin\", \"users\".\"confirmation_token\", \"users\".\"confirmed_at\", \"users\".\"confirmation_sent_at\", \"users\".\"unconfirmed_email\", \"users\".\"locale\", \"users\".\"encrypted_otp_secret\", \"users\".\"encrypted_otp_secret_iv\", \"users\".\"encrypted_otp_secret_salt\", \"users\".\"consumed_timestep\", \"users\".\"otp_required_for_login\", \"users\".\"last_emailed_at\", \"users\".\"otp_backup_codes\", \"users\".\"account_id\", \"users\".\"disabled\", \"users\".\"moderator\", \"users\".\"invite_id\", \"users\".\"chosen_languages\", \"users\".\"created_by_application_id\", \"users\".\"approved\", \"users\".\"sign_in_token\", \"users\".\"sign_in_token_sent_at\", \"users\".\"webauthn_id\", \"users\".\"sign_up_ip\", \"users\".\"role_id\", \"users\".\"settings\", \"users\".\"time_zone\" FROM \"users\" WHERE \"users\".\"account_id\" = $1 LIMIT $2","database_type":"postgres"}},{"id":2854085,"event":"return","thread_id":9160,"parent_id":2854084,"elapsed":0.000467919,"elapsed_instrumentation":8.285604417324066e-05},{"id":2854086,"event":"call","thread_id":9160,"sql_query":{"sql":"SELECT \"devices\".* FROM \"devices\" WHERE \"devices\".\"account_id\" = $1","database_type":"postgres"}},{"id":2854087,"event":"return","thread_id":9160,"parent_id":2854086,"elapsed":0.000551986,"elapsed_instrumentation":0.00019218097440898418},{"id":2854088,"event":"call","thread_id":9160,"sql_query":{"sql":"SELECT \"statuses\".* FROM \"statuses\" WHERE \"statuses\".\"deleted_at\" IS NULL AND \"statuses\".\"account_id\" = $1 ORDER BY \"statuses\".\"id\" DESC","database_type":"postgres"}},{"id":2854089,"event":"return","thread_id":9160,"parent_id":2854088,"elapsed":0.000764792,"elapsed_instrumentation":9.000097634270787e-05},{"id":2854090,"event":"call","thread_id":9160,"sql_query":{"sql":"SELECT \"favourites\".* FROM \"favourites\" WHERE \"favourites\".\"account_id\" = $1","database_type":"postgres"}},{"id":2854091,"event":"return","thread_id":9160,"parent_id":2854090,"elapsed":0.000387225,"elapsed_instrumentation":0.00015812600031495094},{"id":2854092,"event":"call","thread_id":9160,"sql_query":{"sql":"SELECT \"bookmarks\".* FROM \"bookmarks\" WHERE \"bookmarks\".\"account_id\" = $1","database_type":"postgres"}},{"id":2854093,"event":"return","thread_id":9160,"parent_id":2854092,"elapsed":0.000514324,"elapsed_instrumentation":7.667700992897153e-05},{"id":2854094,"event":"call","thread_id":9160,"sql_query":{"sql":"SELECT \"mentions\".* FROM \"mentions\" WHERE \"mentions\".\"account_id\" = $1","database_type":"postgres"}},{"id":2854095,"event":"return","thread_id":9160,"parent_id":2854094,"elapsed":0.00037782,"elapsed_instrumentation":6.759795360267162e-05},{"id":2854096,"event":"call","thread_id":9160,"sql_query":{"sql":"SELECT \"notifications\".* FROM \"notifications\" WHERE \"notifications\".\"account_id\" = $1","database_type":"postgres"}},{"id":2854097,"event":"return","thread_id":9160,"parent_id":2854096,"elapsed":0.000523222,"elapsed_instrumentation":6.863498128950596e-05},{"id":2854098,"event":"call","thread_id":9160,"sql_query":{"sql":"SELECT \"account_conversations\".* FROM \"account_conversations\" WHERE \"account_conversations\".\"account_id\" = $1","database_type":"postgres"}},{"id":2854099,"event":"return","thread_id":9160,"parent_id":2854098,"elapsed":0.000429329,"elapsed_instrumentation":6.680400110781193e-05},{"id":2854100,"event":"call","thread_id":9160,"sql_query":{"sql":"SELECT \"scheduled_statuses\".* FROM \"scheduled_statuses\" WHERE \"scheduled_statuses\".\"account_id\" = $1","database_type":"postgres"}},{"id":2854101,"event":"return","thread_id":9160,"parent_id":2854100,"elapsed":0.000510356,"elapsed_instrumentation":7.218302926048636e-05},{"id":2854102,"event":"call","thread_id":9160,"sql_query":{"sql":"SELECT \"status_pins\".* FROM \"status_pins\" WHERE \"status_pins\".\"account_id\" = $1","database_type":"postgres"}},{"id":2854103,"event":"return","thread_id":9160,"parent_id":2854102,"elapsed":0.000484676,"elapsed_instrumentation":6.953300908207893e-05},{"id":2854104,"event":"call","thread_id":13276700,"defined_class":"RequestPool","method_id":"flush","path":"app/lib/request_pool.rb","lineno":114,"static":false,"parameters":[{"name":"*","class":"Array","object_id":13980800,"value":"[]","kind":"rest","size":0},{"name":"**","class":"Hash","object_id":13980820,"value":"{}","kind":"keyrest","size":0},{"name":"&","class":"NilClass","object_id":4,"value":null,"kind":"block"}],"receiver":{"class":"RequestPool","object_id":13276720,"value":"#<RequestPool:0x00007fc937dbdb90>"}},{"id":2854105,"event":"call","thread_id":13276700,"defined_class":"ConnectionPool::SharedConnectionPool","method_id":"flush","path":"app/lib/connection_pool/shared_connection_pool.rb","lineno":13,"static":false,"parameters":[{"name":"*","class":"Array","object_id":13980840,"value":"[]","kind":"rest","size":0},{"name":"**","class":"Hash","object_id":13980860,"value":"{}","kind":"keyrest","size":0},{"name":"&","class":"NilClass","object_id":4,"value":null,"kind":"block"}],"receiver":{"class":"ConnectionPool::SharedConnectionPool","object_id":13276740,"value":"#<ConnectionPool::SharedConnectionPool:0x00007fc93772a698>"}},{"id":2854106,"event":"call","thread_id":13276700,"defined_class":"ConnectionPool::SharedTimedStack","method_id":"flush","path":"app/lib/connection_pool/shared_timed_stack.rb","lineno":51,"static":false,"parameters":[],"receiver":{"class":"ConnectionPool::SharedTimedStack","object_id":13276780,"value":"#<ConnectionPool::SharedTimedStack:0x00007fc93772a5a8>"}},{"id":2854107,"event":"return","thread_id":13276700,"parent_id":2854106,"elapsed":6.112968549132347e-06,"elapsed_instrumentation":0.0001040319912135601,"return_value":{"class":"Array","value":"[]","object_id":13277080,"size":0}},{"id":2854108,"event":"return","thread_id":13276700,"parent_id":2854105,"elapsed":0.00013063399819657207,"elapsed_instrumentation":0.00011358805932104588,"return_value":{"class":"Array","value":"[]","object_id":13277080,"size":0}},{"id":2854109,"event":"return","thread_id":13276700,"parent_id":2854104,"elapsed":0.0002660580212250352,"elapsed_instrumentation":0.0002679200260899961,"return_value":{"class":"Array","value":"[]","object_id":13277080,"size":0}},{"id":2854110,"event":"call","thread_id":9160,"sql_query":{"sql":"SELECT \"account_pins\".* FROM \"account_pins\" WHERE \"account_pins\".\"account_id\" = $1","database_type":"postgres"}},{"id":2854111,"event":"return","thread_id":9160,"parent_id":2854110,"elapsed":0.000797872,"elapsed_instrumentation":6.941298488527536e-05},{"id":2854112,"event":"call","thread_id":9160,"sql_query":{"sql":"SELECT \"media_attachments\".* FROM \"media_attachments\" WHERE \"media_attachments\".\"account_id\" = $1 ORDER BY \"media_attachments\".\"id\" ASC","database_type":"postgres"}},{"id":2854113,"event":"return","thread_id":9160,"parent_id":2854112,"elapsed":0.000600927,"elapsed_instrumentation":6.76030176691711e-05},{"id":2854114,"event":"call","thread_id":9160,"sql_query":{"sql":"SELECT \"polls\".* FROM \"polls\" WHERE \"polls\".\"account_id\" = $1","database_type":"postgres"}},{"id":2854115,"event":"return","thread_id":9160,"parent_id":2854114,"elapsed":0.000466796,"elapsed_instrumentation":0.00017232802929356694},{"id":2854116,"event":"call","thread_id":9160,"sql_query":{"sql":"SELECT \"reports\".\"id\", \"reports\".\"status_ids\", \"reports\".\"comment\", \"reports\".\"created_at\", \"reports\".\"updated_at\", \"reports\".\"account_id\", \"reports\".\"action_taken_by_account_id\", \"reports\".\"target_account_id\", \"reports\".\"assigned_account_id\", \"reports\".\"uri\", \"reports\".\"forwarded\", \"reports\".\"category\", \"reports\".\"action_taken_at\", \"reports\".\"rule_ids\" FROM \"reports\" WHERE \"reports\".\"account_id\" = $1","database_type":"postgres"}},{"id":2854117,"event":"return","thread_id":9160,"parent_id":2854116,"elapsed":0.000527502,"elapsed_instrumentation":7.904000813141465e-05},{"id":2854118,"event":"call","thread_id":9160,"sql_query":{"sql":"SELECT \"reports\".\"id\", \"reports\".\"status_ids\", \"reports\".\"comment\", \"reports\".\"created_at\", \"reports\".\"updated_at\", \"reports\".\"account_id\", \"reports\".\"action_taken_by_account_id\", \"reports\".\"target_account_id\", \"reports\".\"assigned_account_id\", \"reports\".\"uri\", \"reports\".\"forwarded\", \"reports\".\"category\", \"reports\".\"action_taken_at\", \"reports\".\"rule_ids\" FROM \"reports\" WHERE \"reports\".\"target_account_id\" = $1","database_type":"postgres"}},{"id":2854119,"event":"return","thread_id":9160,"parent_id":2854118,"elapsed":0.000625409,"elapsed_instrumentation":7.515697507187724e-05},{"id":2854120,"event":"call","thread_id":9160,"sql_query":{"sql":"SELECT \"report_notes\".* FROM \"report_notes\" WHERE \"report_notes\".\"account_id\" = $1","database_type":"postgres"}},{"id":2854121,"event":"return","thread_id":9160,"parent_id":2854120,"elapsed":0.000537431,"elapsed_instrumentation":6.907898932695389e-05},{"id":2854122,"event":"call","thread_id":9160,"sql_query":{"sql":"SELECT \"custom_filters\".\"id\", \"custom_filters\".\"account_id\", \"custom_filters\".\"expires_at\", \"custom_filters\".\"phrase\", \"custom_filters\".\"context\", \"custom_filters\".\"created_at\", \"custom_filters\".\"updated_at\", \"custom_filters\".\"action\" FROM \"custom_filters\" WHERE \"custom_filters\".\"account_id\" = $1","database_type":"postgres"}},{"id":2854123,"event":"return","thread_id":9160,"parent_id":2854122,"elapsed":0.000628406,"elapsed_instrumentation":8.556799730286002e-05},{"id":2854124,"event":"call","thread_id":9160,"sql_query":{"sql":"SELECT \"account_moderation_notes\".* FROM \"account_moderation_notes\" WHERE \"account_moderation_notes\".\"account_id\" = $1","database_type":"postgres"}},{"id":2854125,"event":"return","thread_id":9160,"parent_id":2854124,"elapsed":0.000588179,"elapsed_instrumentation":8.738302858546376e-05},{"id":2854126,"event":"call","thread_id":9160,"sql_query":{"sql":"SELECT \"account_moderation_notes\".* FROM \"account_moderation_notes\" WHERE \"account_moderation_notes\".\"target_account_id\" = $1","database_type":"postgres"}},{"id":2854127,"event":"return","thread_id":9160,"parent_id":2854126,"elapsed":0.000585967,"elapsed_instrumentation":0.0001057499903254211},{"id":2854128,"event":"call","thread_id":9160,"sql_query":{"sql":"SELECT \"account_warnings\".* FROM \"account_warnings\" WHERE \"account_warnings\".\"account_id\" = $1","database_type":"postgres"}},{"id":2854129,"event":"return","thread_id":9160,"parent_id":2854128,"elapsed":0.000686166,"elapsed_instrumentation":8.73110257089138e-05},{"id":2854130,"event":"call","thread_id":9160,"sql_query":{"sql":"SELECT \"account_warnings\".* FROM \"account_warnings\" WHERE \"account_warnings\".\"target_account_id\" = $1","database_type":"postgres"}},{"id":2854131,"event":"return","thread_id":9160,"parent_id":2854130,"elapsed":0.000469292,"elapsed_instrumentation":7.994304178282619e-05},{"id":2854132,"event":"call","thread_id":9160,"sql_query":{"sql":"SELECT \"list_accounts\".* FROM \"list_accounts\" WHERE \"list_accounts\".\"account_id\" = $1","database_type":"postgres"}},{"id":2854133,"event":"return","thread_id":9160,"parent_id":2854132,"elapsed":0.000477908,"elapsed_instrumentation":7.967301644384861e-05},{"id":2854134,"event":"call","thread_id":9160,"sql_query":{"sql":"SELECT \"lists\".* FROM \"lists\" WHERE \"lists\".\"account_id\" = $1","database_type":"postgres"}},{"id":2854135,"event":"return","thread_id":9160,"parent_id":2854134,"elapsed":0.000554971,"elapsed_instrumentation":7.026595994830132e-05},{"id":2854136,"event":"call","thread_id":9160,"sql_query":{"sql":"SELECT \"account_migrations\".* FROM \"account_migrations\" WHERE \"account_migrations\".\"account_id\" = $1","database_type":"postgres"}},{"id":2854137,"event":"return","thread_id":9160,"parent_id":2854136,"elapsed":0.000481433,"elapsed_instrumentation":6.894499529153109e-05},{"id":2854138,"event":"call","thread_id":9160,"sql_query":{"sql":"SELECT \"account_aliases\".* FROM \"account_aliases\" WHERE \"account_aliases\".\"account_id\" = $1","database_type":"postgres"}},{"id":2854139,"event":"return","thread_id":9160,"parent_id":2854138,"elapsed":0.000540723,"elapsed_instrumentation":6.871402729302645e-05},{"id":2854140,"event":"call","thread_id":9160,"sql_query":{"sql":"SELECT \"featured_tags\".* FROM \"featured_tags\" WHERE \"featured_tags\".\"account_id\" = $1","database_type":"postgres"}},{"id":2854141,"event":"return","thread_id":9160,"parent_id":2854140,"elapsed":0.000450979,"elapsed_instrumentation":6.691302405670285e-05},{"id":2854142,"event":"call","thread_id":9160,"sql_query":{"sql":"SELECT \"account_deletion_requests\".* FROM \"account_deletion_requests\" WHERE \"account_deletion_requests\".\"account_id\" = $1 LIMIT $2","database_type":"postgres"}},{"id":2854143,"event":"return","thread_id":9160,"parent_id":2854142,"elapsed":0.000444561,"elapsed_instrumentation":6.70679728500545e-05},{"id":2854144,"event":"call","thread_id":9160,"sql_query":{"sql":"SELECT \"follow_recommendation_suppressions\".* FROM \"follow_recommendation_suppressions\" WHERE \"follow_recommendation_suppressions\".\"account_id\" = $1 LIMIT $2","database_type":"postgres"}},{"id":2854145,"event":"return","thread_id":9160,"parent_id":2854144,"elapsed":0.000481822,"elapsed_instrumentation":7.944402750581503e-05},{"id":2854146,"event":"call","thread_id":9160,"sql_query":{"sql":"SELECT \"account_statuses_cleanup_policies\".* FROM \"account_statuses_cleanup_policies\" WHERE \"account_statuses_cleanup_policies\".\"account_id\" = $1 LIMIT $2","database_type":"postgres"}},{"id":2854147,"event":"return","thread_id":9160,"parent_id":2854146,"elapsed":0.000536861,"elapsed_instrumentation":6.936897989362478e-05},{"id":2854148,"event":"call","thread_id":9160,"sql_query":{"sql":"DELETE FROM \"bulk_imports\" WHERE \"bulk_imports\".\"account_id\" = $1","database_type":"postgres"}},{"id":2854149,"event":"return","thread_id":9160,"parent_id":2854148,"elapsed":0.00062744,"elapsed_instrumentation":6.974296411499381e-05},{"id":2854150,"event":"call","thread_id":9160,"sql_query":{"sql":"SELECT \"follow_requests\".* FROM \"follow_requests\" WHERE \"follow_requests\".\"account_id\" = $1","database_type":"postgres"}},{"id":2854151,"event":"return","thread_id":9160,"parent_id":2854150,"elapsed":0.000541855,"elapsed_instrumentation":7.273000665009022e-05},{"id":2854152,"event":"call","thread_id":9160,"sql_query":{"sql":"SELECT \"follows\".* FROM \"follows\" WHERE \"follows\".\"account_id\" = $1","database_type":"postgres"}},{"id":2854153,"event":"return","thread_id":9160,"parent_id":2854152,"elapsed":0.000504828,"elapsed_instrumentation":7.934804307296872e-05},{"id":2854154,"event":"call","thread_id":9160,"sql_query":{"sql":"SELECT \"follows\".* FROM \"follows\" WHERE \"follows\".\"target_account_id\" = $1","database_type":"postgres"}},{"id":2854155,"event":"return","thread_id":9160,"parent_id":2854154,"elapsed":0.000465016,"elapsed_instrumentation":7.445801747962832e-05},{"id":2854156,"event":"call","thread_id":9160,"sql_query":{"sql":"SELECT \"account_notes\".* FROM \"account_notes\" WHERE \"account_notes\".\"account_id\" = $1","database_type":"postgres"}},{"id":2854157,"event":"return","thread_id":9160,"parent_id":2854156,"elapsed":0.000599615,"elapsed_instrumentation":0.00015364499995484948},{"id":2854158,"event":"call","thread_id":9160,"sql_query":{"sql":"SELECT \"blocks\".* FROM \"blocks\" WHERE \"blocks\".\"account_id\" = $1","database_type":"postgres"}},{"id":2854159,"event":"return","thread_id":9160,"parent_id":2854158,"elapsed":0.0004585,"elapsed_instrumentation":8.179800352081656e-05},{"id":2854160,"event":"call","thread_id":9160,"sql_query":{"sql":"SELECT \"blocks\".* FROM \"blocks\" WHERE \"blocks\".\"target_account_id\" = $1","database_type":"postgres"}},{"id":2854161,"event":"return","thread_id":9160,"parent_id":2854160,"elapsed":0.000408251,"elapsed_instrumentation":6.844400195404887e-05},{"id":2854162,"event":"call","thread_id":9160,"sql_query":{"sql":"SELECT \"mutes\".* FROM \"mutes\" WHERE \"mutes\".\"account_id\" = $1","database_type":"postgres"}},{"id":2854163,"event":"return","thread_id":9160,"parent_id":2854162,"elapsed":0.000412081,"elapsed_instrumentation":6.736000068485737e-05},{"id":2854164,"event":"call","thread_id":9160,"sql_query":{"sql":"SELECT \"mutes\".* FROM \"mutes\" WHERE \"mutes\".\"target_account_id\" = $1","database_type":"postgres"}},{"id":2854165,"event":"return","thread_id":9160,"parent_id":2854164,"elapsed":0.000402411,"elapsed_instrumentation":7.027696119621396e-05},{"id":2854166,"event":"call","thread_id":9160,"sql_query":{"sql":"SELECT \"conversation_mutes\".* FROM \"conversation_mutes\" WHERE \"conversation_mutes\".\"account_id\" = $1","database_type":"postgres"}},{"id":2854167,"event":"return","thread_id":9160,"parent_id":2854166,"elapsed":0.000614165,"elapsed_instrumentation":8.298101602122188e-05},{"id":2854168,"event":"call","thread_id":9160,"sql_query":{"sql":"SELECT \"account_domain_blocks\".* FROM \"account_domain_blocks\" WHERE \"account_domain_blocks\".\"account_id\" = $1","database_type":"postgres"}},{"id":2854169,"event":"return","thread_id":9160,"parent_id":2854168,"elapsed":0.000622057,"elapsed_instrumentation":8.414301555603743e-05},{"id":2854170,"event":"call","thread_id":9160,"sql_query":{"sql":"SELECT \"announcement_mutes\".* FROM \"announcement_mutes\" WHERE \"announcement_mutes\".\"account_id\" = $1","database_type":"postgres"}},{"id":2854171,"event":"return","thread_id":9160,"parent_id":2854170,"elapsed":0.000544962,"elapsed_instrumentation":6.86459825374186e-05},{"id":2854172,"event":"call","thread_id":9160,"defined_class":"FeedManager","method_id":"clean_feeds!","path":"app/lib/feed_manager.rb","lineno":294,"static":false,"parameters":[{"name":"type","class":"Symbol","object_id":426588,"value":":home","kind":"req"},{"name":"ids","class":"Array","object_id":13980880,"value":"[111361437184298728]","kind":"req","size":1}],"receiver":{"class":"FeedManager","object_id":496900,"value":"#<FeedManager:0x00007fc932f2fde8>"}},{"id":2854173,"event":"call","thread_id":9160,"defined_class":"Redisable","method_id":"redis","path":"app/models/concerns/redisable.rb","lineno":4,"static":false,"parameters":[],"receiver":{"class":"FeedManager","object_id":496900,"value":"#<FeedManager:0x00007fc932f2fde8>"}},{"id":2854174,"event":"return","thread_id":9160,"parent_id":2854173,"elapsed":5.9710000641644e-06,"elapsed_instrumentation":8.48660129122436e-05,"return_value":{"class":"Redis::Namespace","value":"#<Redis::Namespace:0x00007fc934c37e90>","object_id":319760}},{"id":2854175,"event":"call","thread_id":9160,"defined_class":"FeedManager","method_id":"key","path":"app/lib/feed_manager.rb","lineno":29,"static":false,"parameters":[{"name":"type","class":"Symbol","object_id":426588,"value":":home","kind":"req"},{"name":"id","class":"Integer","object_id":222722874368597457,"value":"111361437184298728","kind":"req"},{"name":"subtype","class":"String","object_id":497080,"value":"reblogs","kind":"opt"}],"receiver":{"class":"FeedManager","object_id":496900,"value":"#<FeedManager:0x00007fc932f2fde8>"}},{"id":2854176,"event":"return","thread_id":9160,"parent_id":2854175,"elapsed":7.06501305103302e-06,"elapsed_instrumentation":0.00011002406245097518,"return_value":{"class":"String","value":"feed:home:111361437184298728:reblogs","object_id":13980900}},{"id":2854177,"event":"call","thread_id":9160,"defined_class":"FeedManager","method_id":"key","path":"app/lib/feed_manager.rb","lineno":29,"static":false,"parameters":[{"name":"type","class":"Symbol","object_id":426588,"value":":home","kind":"req"},{"name":"id","class":"Integer","object_id":222722874368597457,"value":"111361437184298728","kind":"req"},{"name":"subtype","class":"NilClass","object_id":4,"value":null,"kind":"opt"}],"receiver":{"class":"FeedManager","object_id":496900,"value":"#<FeedManager:0x00007fc932f2fde8>"}},{"id":2854178,"event":"return","thread_id":9160,"parent_id":2854177,"elapsed":4.185945726931095e-06,"elapsed_instrumentation":9.989307727664709e-05,"return_value":{"class":"String","value":"feed:home:111361437184298728","object_id":13980920}},{"id":2854179,"event":"return","thread_id":9160,"parent_id":2854172,"elapsed":0.0008794949972070754,"elapsed_instrumentation":0.00018264399841427803},{"id":2854180,"event":"return","thread_id":9160,"parent_id":2854081,"elapsed":0.07050457602599636,"elapsed_instrumentation":0.00023239600704982877,"return_value":{"class":"Array","value":"[#<Proc:0x00007fc931571348 /workspaces/mastodon/vendor/bundle/ruby/3.2.0/gems/activesupport-7.1.1/lib, #<Proc:0x00007fc931571488 /workspaces/mastodon/vendor/bundle/ruby/3.2.0/gems/activesupport-7.1.1/lib, #<Proc:0x00007fc9315715c8 /workspaces/mastodon/vendor/bundle/ruby/3.2.0/gems/activesupport-7.1.1/lib, #<Proc:0x00007fc931571708 /workspaces/mastodon/vendor/bundle/ruby/3.2.0/gems/activesupport-7.1.1/lib, #<Proc:0x00007fc931571848 /workspaces/mastodon/vendor/bundle/ruby/3.2.0/gems/activesupport-7.1.1/lib, #<Proc:0x00007fc931571988 /workspaces/mastodon/vendor/bundle/ruby/3.2.0/gems/activesupport-7.1.1/lib, #<Proc:0x00007fc931571af0 /workspaces/mastodon/vendor/bundle/ruby/3.2.0/gems/activesupport-7.1.1/lib, #<Proc:0x00007fc931571c30 /workspaces/mastodon/vendor/bundle/ruby/3.2.0/gems/activesupport-7.1.1/lib, #<Proc:0x00007fc931571de8 /workspaces/mastodon/vendor/bundle/ruby/3.2.0/gems/activesupport-7.1.1/lib, #<Proc:0x00007fc931571f78 /workspaces/mastodon/vendor/bundle/ruby/3.2.0/gems/activesupport-7.1.1/lib (...34 more items)]","object_id":5268780,"size":44}},{"id":2854181,"event":"call","thread_id":9160,"sql_query":{"sql":"DELETE FROM \"accounts_tags\" WHERE \"accounts_tags\".\"account_id\" = $1","database_type":"postgres"}},{"id":2854182,"event":"return","thread_id":9160,"parent_id":2854181,"elapsed":0.000608706,"elapsed_instrumentation":7.495097815990448e-05},{"id":2854183,"event":"call","thread_id":9160,"sql_query":{"sql":"DELETE FROM \"accounts\" WHERE \"accounts\".\"id\" = $1","database_type":"postgres"}},{"id":2854184,"event":"return","thread_id":9160,"parent_id":2854183,"elapsed":0.00756709,"elapsed_instrumentation":7.478997576981783e-05},{"id":2854185,"event":"call","thread_id":9160,"defined_class":"ActiveSupport::Callbacks::CallbackSequence","method_id":"invoke_after","path":"vendor/bundle/ruby/3.2.0/gems/activesupport-7.1.1/lib/active_support/callbacks.rb","lineno":601,"static":false,"parameters":[{"name":"arg","class":"ActiveSupport::Callbacks::Filters::Environment","object_id":13980780,"value":null,"kind":"req"}],"receiver":{"class":"ActiveSupport::Callbacks::CallbackSequence","object_id":5268680,"value":"#<ActiveSupport::Callbacks::CallbackSequence:0x00007fc930d01c30>"}},{"id":2854186,"event":"return","thread_id":9160,"parent_id":2854185,"elapsed":0.00011341902427375317,"elapsed_instrumentation":0.00016325293108820915,"return_value":{"class":"Array","value":"[#<Proc:0x00007fc931571190 /workspaces/mastodon/vendor/bundle/ruby/3.2.0/gems/activesupport-7.1.1/lib]","object_id":5268840,"size":1}},{"id":2854187,"event":"call","thread_id":9160,"sql_query":{"sql":"RELEASE SAVEPOINT active_record_1","database_type":"postgres"}},{"id":2854188,"event":"return","thread_id":9160,"parent_id":2854187,"elapsed":0.000596843,"elapsed_instrumentation":7.808103691786528e-05},{"id":2854189,"event":"call","thread_id":9160,"defined_class":"ActiveSupport::Callbacks::CallbackSequence","method_id":"invoke_before","path":"vendor/bundle/ruby/3.2.0/gems/activesupport-7.1.1/lib/active_support/callbacks.rb","lineno":597,"static":false,"parameters":[{"name":"arg","class":"ActiveSupport::Callbacks::Filters::Environment","object_id":13980940,"value":null,"kind":"req"}],"receiver":{"class":"ActiveSupport::Callbacks::CallbackSequence","object_id":328280,"value":"#<ActiveSupport::Callbacks::CallbackSequence:0x00007fc9378db2d0>"}},{"id":2854190,"event":"return","thread_id":9160,"parent_id":2854189,"elapsed":3.947003278881311e-06,"elapsed_instrumentation":0.00012211099965497851,"return_value":{"class":"Array","value":"[]","object_id":328300,"size":0}},{"id":2854191,"event":"call","thread_id":9160,"defined_class":"ActiveSupport::Callbacks::CallbackSequence","method_id":"invoke_after","path":"vendor/bundle/ruby/3.2.0/gems/activesupport-7.1.1/lib/active_support/callbacks.rb","lineno":601,"static":false,"parameters":[{"name":"arg","class":"ActiveSupport::Callbacks::Filters::Environment","object_id":13980940,"value":null,"kind":"req"}],"receiver":{"class":"ActiveSupport::Callbacks::CallbackSequence","object_id":328280,"value":"#<ActiveSupport::Callbacks::CallbackSequence:0x00007fc9378db2d0>"}},{"id":2854192,"event":"return","thread_id":9160,"parent_id":2854191,"elapsed":0.00018987199291586876,"elapsed_instrumentation":0.0001622270210646093,"return_value":{"class":"Array","value":"[#<Proc:0x00007fc938945850 /workspaces/mastodon/vendor/bundle/ruby/3.2.0/gems/activesupport-7.1.1/lib, #<Proc:0x00007fc938942a10 /workspaces/mastodon/vendor/bundle/ruby/3.2.0/gems/activesupport-7.1.1/lib, #<Proc:0x00007fc93855fba0 /workspaces/mastodon/vendor/bundle/ruby/3.2.0/gems/activesupport-7.1.1/lib, #<Proc:0x00007fc93855f0b0 /workspaces/mastodon/vendor/bundle/ruby/3.2.0/gems/activesupport-7.1.1/lib, #<Proc:0x00007fc93855ebb0 /workspaces/mastodon/vendor/bundle/ruby/3.2.0/gems/activesupport-7.1.1/lib, #<Proc:0x00007fc93855de40 /workspaces/mastodon/vendor/bundle/ruby/3.2.0/gems/activesupport-7.1.1/lib]","object_id":328320,"size":6}},{"id":2854193,"event":"call","thread_id":9160,"defined_class":"Account","method_id":"bot","path":"app/models/account.rb","lineno":171,"static":false,"parameters":[],"receiver":{"class":"Account","object_id":13980960,"value":"#<Account:0x00007fc8e21d26c8>"}},{"id":2854194,"event":"return","thread_id":9160,"parent_id":2854193,"elapsed":2.2945983801037073e-05,"elapsed_instrumentation":7.708597695454955e-05},{"id":2854195,"event":"call","thread_id":9160,"defined_class":"Account","method_id":"group","path":"app/models/account.rb","lineno":185,"static":false,"parameters":[],"receiver":{"class":"Account","object_id":13980960,"value":"#<Account:0x00007fc8e21d26c8>"}},{"id":2854196,"event":"return","thread_id":9160,"parent_id":2854195,"elapsed":5.073961801826954e-06,"elapsed_instrumentation":5.66940288990736e-05},{"id":2854197,"event":"call","thread_id":9160,"defined_class":"Account","method_id":"suspended?","path":"app/models/account.rb","lineno":237,"static":false,"parameters":[],"receiver":{"class":"Account","object_id":13980960,"value":"#<Account:0x00007fc8e21d26c8>"}},{"id":2854198,"event":"return","thread_id":9160,"parent_id":2854197,"elapsed":2.0934967324137688e-05,"elapsed_instrumentation":5.266204243525863e-05},{"id":2854199,"event":"call","thread_id":9160,"defined_class":"Account","method_id":"silenced?","path":"app/models/account.rb","lineno":225,"static":false,"parameters":[],"receiver":{"class":"Account","object_id":13980960,"value":"#<Account:0x00007fc8e21d26c8>"}},{"id":2854200,"event":"return","thread_id":9160,"parent_id":2854199,"elapsed":1.1964002624154091e-05,"elapsed_instrumentation":5.0659000407904387e-05},{"id":2854201,"event":"call","thread_id":9160,"defined_class":"ActiveSupport::Callbacks::CallbackSequence","method_id":"invoke_before","path":"vendor/bundle/ruby/3.2.0/gems/activesupport-7.1.1/lib/active_support/callbacks.rb","lineno":597,"static":false,"parameters":[{"name":"arg","class":"ActiveSupport::Callbacks::Filters::Environment","object_id":13980980,"value":null,"kind":"req"}],"receiver":{"class":"ActiveSupport::Callbacks::CallbackSequence","object_id":5268680,"value":"#<ActiveSupport::Callbacks::CallbackSequence:0x00007fc930d01c30>"}},{"id":2854202,"event":"call","thread_id":9160,"sql_query":{"sql":"SAVEPOINT active_record_1","database_type":"postgres"}},{"id":2854203,"event":"return","thread_id":9160,"parent_id":2854202,"elapsed":0.000391325,"elapsed_instrumentation":7.525796536356211e-05},{"id":2854204,"event":"call","thread_id":9160,"sql_query":{"sql":"SELECT \"users\".\"id\", \"users\".\"email\", \"users\".\"created_at\", \"users\".\"updated_at\", \"users\".\"encrypted_password\", \"users\".\"reset_password_token\", \"users\".\"reset_password_sent_at\", \"users\".\"sign_in_count\", \"users\".\"current_sign_in_at\", \"users\".\"last_sign_in_at\", \"users\".\"admin\", \"users\".\"confirmation_token\", \"users\".\"confirmed_at\", \"users\".\"confirmation_sent_at\", \"users\".\"unconfirmed_email\", \"users\".\"locale\", \"users\".\"encrypted_otp_secret\", \"users\".\"encrypted_otp_secret_iv\", \"users\".\"encrypted_otp_secret_salt\", \"users\".\"consumed_timestep\", \"users\".\"otp_required_for_login\", \"users\".\"last_emailed_at\", \"users\".\"otp_backup_codes\", \"users\".\"account_id\", \"users\".\"disabled\", \"users\".\"moderator\", \"users\".\"invite_id\", \"users\".\"chosen_languages\", \"users\".\"created_by_application_id\", \"users\".\"approved\", \"users\".\"sign_in_token\", \"users\".\"sign_in_token_sent_at\", \"users\".\"webauthn_id\", \"users\".\"sign_up_ip\", \"users\".\"role_id\", \"users\".\"settings\", \"users\".\"time_zone\" FROM \"users\" WHERE \"users\".\"account_id\" = $1 LIMIT $2","database_type":"postgres"}},{"id":2854205,"event":"return","thread_id":9160,"parent_id":2854204,"elapsed":0.000452126,"elapsed_instrumentation":7.160805398598313e-05},{"id":2854206,"event":"call","thread_id":9160,"sql_query":{"sql":"SELECT \"devices\".* FROM \"devices\" WHERE \"devices\".\"account_id\" = $1","database_type":"postgres"}},{"id":2854207,"event":"return","thread_id":9160,"parent_id":2854206,"elapsed":0.000460611,"elapsed_instrumentation":0.00017558404942974448},{"id":2854208,"event":"call","thread_id":9160,"sql_query":{"sql":"SELECT \"statuses\".* FROM \"statuses\" WHERE \"statuses\".\"deleted_at\" IS NULL AND \"statuses\".\"account_id\" = $1 ORDER BY \"statuses\".\"id\" DESC","database_type":"postgres"}},{"id":2854209,"event":"return","thread_id":9160,"parent_id":2854208,"elapsed":0.000487104,"elapsed_instrumentation":7.698097033426166e-05},{"id":2854210,"event":"call","thread_id":9160,"sql_query":{"sql":"SELECT \"favourites\".* FROM \"favourites\" WHERE \"favourites\".\"account_id\" = $1","database_type":"postgres"}},{"id":2854211,"event":"return","thread_id":9160,"parent_id":2854210,"elapsed":0.000471777,"elapsed_instrumentation":7.409998215734959e-05},{"id":2854212,"event":"call","thread_id":9160,"sql_query":{"sql":"SELECT \"bookmarks\".* FROM \"bookmarks\" WHERE \"bookmarks\".\"account_id\" = $1","database_type":"postgres"}},{"id":2854213,"event":"return","thread_id":9160,"parent_id":2854212,"elapsed":0.000455642,"elapsed_instrumentation":7.394101703539491e-05},{"id":2854214,"event":"call","thread_id":9160,"sql_query":{"sql":"SELECT \"mentions\".* FROM \"mentions\" WHERE \"mentions\".\"account_id\" = $1","database_type":"postgres"}},{"id":2854215,"event":"return","thread_id":9160,"parent_id":2854214,"elapsed":0.00040245,"elapsed_instrumentation":7.35839712433517e-05},{"id":2854216,"event":"call","thread_id":9160,"sql_query":{"sql":"SELECT \"notifications\".* FROM \"notifications\" WHERE \"notifications\".\"account_id\" = $1","database_type":"postgres"}},{"id":2854217,"event":"return","thread_id":9160,"parent_id":2854216,"elapsed":0.000426259,"elapsed_instrumentation":6.906397175043821e-05},{"id":2854218,"event":"call","thread_id":9160,"sql_query":{"sql":"SELECT \"account_conversations\".* FROM \"account_conversations\" WHERE \"account_conversations\".\"account_id\" = $1","database_type":"postgres"}},{"id":2854219,"event":"return","thread_id":9160,"parent_id":2854218,"elapsed":0.000329009,"elapsed_instrumentation":6.856699474155903e-05},{"id":2854220,"event":"call","thread_id":9160,"sql_query":{"sql":"SELECT \"scheduled_statuses\".* FROM \"scheduled_statuses\" WHERE \"scheduled_statuses\".\"account_id\" = $1","database_type":"postgres"}},{"id":2854221,"event":"return","thread_id":9160,"parent_id":2854220,"elapsed":0.000501039,"elapsed_instrumentation":7.163197733461857e-05},{"id":2854222,"event":"call","thread_id":9160,"sql_query":{"sql":"SELECT \"status_pins\".* FROM \"status_pins\" WHERE \"status_pins\".\"account_id\" = $1","database_type":"postgres"}},{"id":2854223,"event":"return","thread_id":9160,"parent_id":2854222,"elapsed":0.000356602,"elapsed_instrumentation":6.985600339248776e-05},{"id":2854224,"event":"call","thread_id":9160,"sql_query":{"sql":"SELECT \"account_pins\".* FROM \"account_pins\" WHERE \"account_pins\".\"account_id\" = $1","database_type":"postgres"}},{"id":2854225,"event":"return","thread_id":9160,"parent_id":2854224,"elapsed":0.000368084,"elapsed_instrumentation":7.532601011916995e-05},{"id":2854226,"event":"call","thread_id":9160,"sql_query":{"sql":"SELECT \"media_attachments\".* FROM \"media_attachments\" WHERE \"media_attachments\".\"account_id\" = $1 ORDER BY \"media_attachments\".\"id\" ASC","database_type":"postgres"}},{"id":2854227,"event":"return","thread_id":9160,"parent_id":2854226,"elapsed":0.000536318,"elapsed_instrumentation":7.320597069337964e-05},{"id":2854228,"event":"call","thread_id":9160,"sql_query":{"sql":"SELECT \"polls\".* FROM \"polls\" WHERE \"polls\".\"account_id\" = $1","database_type":"postgres"}},{"id":2854229,"event":"return","thread_id":9160,"parent_id":2854228,"elapsed":0.00058699,"elapsed_instrumentation":7.19579984433949e-05},{"id":2854230,"event":"call","thread_id":9160,"sql_query":{"sql":"SELECT \"reports\".\"id\", \"reports\".\"status_ids\", \"reports\".\"comment\", \"reports\".\"created_at\", \"reports\".\"updated_at\", \"reports\".\"account_id\", \"reports\".\"action_taken_by_account_id\", \"reports\".\"target_account_id\", \"reports\".\"assigned_account_id\", \"reports\".\"uri\", \"reports\".\"forwarded\", \"reports\".\"category\", \"reports\".\"action_taken_at\", \"reports\".\"rule_ids\" FROM \"reports\" WHERE \"reports\".\"account_id\" = $1","database_type":"postgres"}},{"id":2854231,"event":"return","thread_id":9160,"parent_id":2854230,"elapsed":0.000451185,"elapsed_instrumentation":9.004899766296148e-05},{"id":2854232,"event":"call","thread_id":9160,"sql_query":{"sql":"SELECT \"reports\".\"id\", \"reports\".\"status_ids\", \"reports\".\"comment\", \"reports\".\"created_at\", \"reports\".\"updated_at\", \"reports\".\"account_id\", \"reports\".\"action_taken_by_account_id\", \"reports\".\"target_account_id\", \"reports\".\"assigned_account_id\", \"reports\".\"uri\", \"reports\".\"forwarded\", \"reports\".\"category\", \"reports\".\"action_taken_at\", \"reports\".\"rule_ids\" FROM \"reports\" WHERE \"reports\".\"target_account_id\" = $1","database_type":"postgres"}},{"id":2854233,"event":"return","thread_id":9160,"parent_id":2854232,"elapsed":0.000626836,"elapsed_instrumentation":9.956001304090023e-05},{"id":2854234,"event":"call","thread_id":9160,"sql_query":{"sql":"SELECT \"report_notes\".* FROM \"report_notes\" WHERE \"report_notes\".\"account_id\" = $1","database_type":"postgres"}},{"id":2854235,"event":"return","thread_id":9160,"parent_id":2854234,"elapsed":0.000542021,"elapsed_instrumentation":9.401002898812294e-05},{"id":2854236,"event":"call","thread_id":9160,"sql_query":{"sql":"SELECT \"custom_filters\".\"id\", \"custom_filters\".\"account_id\", \"custom_filters\".\"expires_at\", \"custom_filters\".\"phrase\", \"custom_filters\".\"context\", \"custom_filters\".\"created_at\", \"custom_filters\".\"updated_at\", \"custom_filters\".\"action\" FROM \"custom_filters\" WHERE \"custom_filters\".\"account_id\" = $1","database_type":"postgres"}},{"id":2854237,"event":"return","thread_id":9160,"parent_id":2854236,"elapsed":0.000646031,"elapsed_instrumentation":0.0001350889797322452},{"id":2854238,"event":"call","thread_id":9160,"sql_query":{"sql":"SELECT \"account_moderation_notes\".* FROM \"account_moderation_notes\" WHERE \"account_moderation_notes\".\"account_id\" = $1","database_type":"postgres"}},{"id":2854239,"event":"return","thread_id":9160,"parent_id":2854238,"elapsed":0.00066864,"elapsed_instrumentation":0.00010078202467411757},{"id":2854240,"event":"call","thread_id":9160,"sql_query":{"sql":"SELECT \"account_moderation_notes\".* FROM \"account_moderation_notes\" WHERE \"account_moderation_notes\".\"target_account_id\" = $1","database_type":"postgres"}},{"id":2854241,"event":"return","thread_id":9160,"parent_id":2854240,"elapsed":0.00065946,"elapsed_instrumentation":8.732796413823962e-05},{"id":2854242,"event":"call","thread_id":13276700,"defined_class":"RequestPool","method_id":"flush","path":"app/lib/request_pool.rb","lineno":114,"static":false,"parameters":[{"name":"*","class":"Array","object_id":13981000,"value":"[]","kind":"rest","size":0},{"name":"**","class":"Hash","object_id":13981020,"value":"{}","kind":"keyrest","size":0},{"name":"&","class":"NilClass","object_id":4,"value":null,"kind":"block"}],"receiver":{"class":"RequestPool","object_id":13276720,"value":"#<RequestPool:0x00007fc937dbdb90>"}},{"id":2854243,"event":"call","thread_id":13276700,"defined_class":"ConnectionPool::SharedConnectionPool","method_id":"flush","path":"app/lib/connection_pool/shared_connection_pool.rb","lineno":13,"static":false,"parameters":[{"name":"*","class":"Array","object_id":13981040,"value":"[]","kind":"rest","size":0},{"name":"**","class":"Hash","object_id":13981060,"value":"{}","kind":"keyrest","size":0},{"name":"&","class":"NilClass","object_id":4,"value":null,"kind":"block"}],"receiver":{"class":"ConnectionPool::SharedConnectionPool","object_id":13276740,"value":"#<ConnectionPool::SharedConnectionPool:0x00007fc93772a698>"}},{"id":2854244,"event":"call","thread_id":13276700,"defined_class":"ConnectionPool::SharedTimedStack","method_id":"flush","path":"app/lib/connection_pool/shared_timed_stack.rb","lineno":51,"static":false,"parameters":[],"receiver":{"class":"ConnectionPool::SharedTimedStack","object_id":13276780,"value":"#<ConnectionPool::SharedTimedStack:0x00007fc93772a5a8>"}},{"id":2854245,"event":"return","thread_id":13276700,"parent_id":2854244,"elapsed":6.393005605787039e-06,"elapsed_instrumentation":7.996999192982912e-05,"return_value":{"class":"Array","value":"[]","object_id":13277080,"size":0}},{"id":2854246,"event":"return","thread_id":13276700,"parent_id":2854243,"elapsed":0.00010833999840542674,"elapsed_instrumentation":0.00015245599206537008,"return_value":{"class":"Array","value":"[]","object_id":13277080,"size":0}},{"id":2854247,"event":"return","thread_id":13276700,"parent_id":2854242,"elapsed":0.00028747302712872624,"elapsed_instrumentation":0.00021312799071893096,"return_value":{"class":"Array","value":"[]","object_id":13277080,"size":0}},{"id":2854248,"event":"call","thread_id":9160,"sql_query":{"sql":"SELECT \"account_warnings\".* FROM \"account_warnings\" WHERE \"account_warnings\".\"account_id\" = $1","database_type":"postgres"}},{"id":2854249,"event":"return","thread_id":9160,"parent_id":2854248,"elapsed":0.000835168,"elapsed_instrumentation":8.432898903265595e-05},{"id":2854250,"event":"call","thread_id":9160,"sql_query":{"sql":"SELECT \"account_warnings\".* FROM \"account_warnings\" WHERE \"account_warnings\".\"target_account_id\" = $1","database_type":"postgres"}},{"id":2854251,"event":"return","thread_id":9160,"parent_id":2854250,"elapsed":0.000438179,"elapsed_instrumentation":8.528598118573427e-05},{"id":2854252,"event":"call","thread_id":9160,"sql_query":{"sql":"SELECT \"list_accounts\".* FROM \"list_accounts\" WHERE \"list_accounts\".\"account_id\" = $1","database_type":"postgres"}},{"id":2854253,"event":"return","thread_id":9160,"parent_id":2854252,"elapsed":0.000504586,"elapsed_instrumentation":8.431496098637581e-05},{"id":2854254,"event":"call","thread_id":9160,"sql_query":{"sql":"SELECT \"lists\".* FROM \"lists\" WHERE \"lists\".\"account_id\" = $1","database_type":"postgres"}},{"id":2854255,"event":"return","thread_id":9160,"parent_id":2854254,"elapsed":0.000336753,"elapsed_instrumentation":6.978696910664439e-05},{"id":2854256,"event":"call","thread_id":9160,"sql_query":{"sql":"SELECT \"account_migrations\".* FROM \"account_migrations\" WHERE \"account_migrations\".\"account_id\" = $1","database_type":"postgres"}},{"id":2854257,"event":"return","thread_id":9160,"parent_id":2854256,"elapsed":0.000510173,"elapsed_instrumentation":8.361699292436242e-05},{"id":2854258,"event":"call","thread_id":9160,"sql_query":{"sql":"SELECT \"account_aliases\".* FROM \"account_aliases\" WHERE \"account_aliases\".\"account_id\" = $1","database_type":"postgres"}},{"id":2854259,"event":"return","thread_id":9160,"parent_id":2854258,"elapsed":0.000549978,"elapsed_instrumentation":0.0003030060324817896},{"id":2854260,"event":"call","thread_id":9160,"sql_query":{"sql":"SELECT \"featured_tags\".* FROM \"featured_tags\" WHERE \"featured_tags\".\"account_id\" = $1","database_type":"postgres"}},{"id":2854261,"event":"return","thread_id":9160,"parent_id":2854260,"elapsed":0.000521429,"elapsed_instrumentation":7.946201367303729e-05},{"id":2854262,"event":"call","thread_id":9160,"sql_query":{"sql":"SELECT \"account_deletion_requests\".* FROM \"account_deletion_requests\" WHERE \"account_deletion_requests\".\"account_id\" = $1 LIMIT $2","database_type":"postgres"}},{"id":2854263,"event":"return","thread_id":9160,"parent_id":2854262,"elapsed":0.000493951,"elapsed_instrumentation":8.620001608505845e-05},{"id":2854264,"event":"call","thread_id":9160,"sql_query":{"sql":"SELECT \"follow_recommendation_suppressions\".* FROM \"follow_recommendation_suppressions\" WHERE \"follow_recommendation_suppressions\".\"account_id\" = $1 LIMIT $2","database_type":"postgres"}},{"id":2854265,"event":"return","thread_id":9160,"parent_id":2854264,"elapsed":0.000610812,"elapsed_instrumentation":9.907298954203725e-05},{"id":2854266,"event":"call","thread_id":9160,"sql_query":{"sql":"SELECT \"account_statuses_cleanup_policies\".* FROM \"account_statuses_cleanup_policies\" WHERE \"account_statuses_cleanup_policies\".\"account_id\" = $1 LIMIT $2","database_type":"postgres"}},{"id":2854267,"event":"return","thread_id":9160,"parent_id":2854266,"elapsed":0.000553783,"elapsed_instrumentation":7.76039669290185e-05},{"id":2854268,"event":"call","thread_id":9160,"sql_query":{"sql":"DELETE FROM \"bulk_imports\" WHERE \"bulk_imports\".\"account_id\" = $1","database_type":"postgres"}},{"id":2854269,"event":"return","thread_id":9160,"parent_id":2854268,"elapsed":0.000594839,"elapsed_instrumentation":7.509300485253334e-05},{"id":2854270,"event":"call","thread_id":9160,"sql_query":{"sql":"SELECT \"follow_requests\".* FROM \"follow_requests\" WHERE \"follow_requests\".\"account_id\" = $1","database_type":"postgres"}},{"id":2854271,"event":"return","thread_id":9160,"parent_id":2854270,"elapsed":0.000596588,"elapsed_instrumentation":7.871503476053476e-05},{"id":2854272,"event":"call","thread_id":9160,"sql_query":{"sql":"SELECT \"follows\".* FROM \"follows\" WHERE \"follows\".\"account_id\" = $1","database_type":"postgres"}},{"id":2854273,"event":"return","thread_id":9160,"parent_id":2854272,"elapsed":0.000578776,"elapsed_instrumentation":0.0001140739768743515},{"id":2854274,"event":"call","thread_id":9160,"sql_query":{"sql":"SELECT \"follows\".* FROM \"follows\" WHERE \"follows\".\"target_account_id\" = $1","database_type":"postgres"}},{"id":2854275,"event":"return","thread_id":9160,"parent_id":2854274,"elapsed":0.000760863,"elapsed_instrumentation":0.0002664289786480367},{"id":2854276,"event":"call","thread_id":9160,"sql_query":{"sql":"SELECT \"account_notes\".* FROM \"account_notes\" WHERE \"account_notes\".\"account_id\" = $1","database_type":"postgres"}},{"id":2854277,"event":"return","thread_id":9160,"parent_id":2854276,"elapsed":0.000635791,"elapsed_instrumentation":9.61099867708981e-05},{"id":2854278,"event":"call","thread_id":9160,"sql_query":{"sql":"SELECT \"blocks\".* FROM \"blocks\" WHERE \"blocks\".\"account_id\" = $1","database_type":"postgres"}},{"id":2854279,"event":"return","thread_id":9160,"parent_id":2854278,"elapsed":0.000495697,"elapsed_instrumentation":9.37409931793809e-05},{"id":2854280,"event":"call","thread_id":9160,"sql_query":{"sql":"SELECT \"blocks\".* FROM \"blocks\" WHERE \"blocks\".\"target_account_id\" = $1","database_type":"postgres"}},{"id":2854281,"event":"return","thread_id":9160,"parent_id":2854280,"elapsed":0.000909458,"elapsed_instrumentation":0.00012416596291586757},{"id":2854282,"event":"call","thread_id":9160,"sql_query":{"sql":"SELECT \"mutes\".* FROM \"mutes\" WHERE \"mutes\".\"account_id\" = $1","database_type":"postgres"}},{"id":2854283,"event":"return","thread_id":9160,"parent_id":2854282,"elapsed":0.000574776,"elapsed_instrumentation":0.0001059030182659626},{"id":2854284,"event":"call","thread_id":9160,"sql_query":{"sql":"SELECT \"mutes\".* FROM \"mutes\" WHERE \"mutes\".\"target_account_id\" = $1","database_type":"postgres"}},{"id":2854285,"event":"return","thread_id":9160,"parent_id":2854284,"elapsed":0.000792663,"elapsed_instrumentation":0.0001688330085016787},{"id":2854286,"event":"call","thread_id":9160,"sql_query":{"sql":"SELECT \"conversation_mutes\".* FROM \"conversation_mutes\" WHERE \"conversation_mutes\".\"account_id\" = $1","database_type":"postgres"}},{"id":2854287,"event":"return","thread_id":9160,"parent_id":2854286,"elapsed":0.000916823,"elapsed_instrumentation":0.00018559099407866597},{"id":2854288,"event":"call","thread_id":9160,"sql_query":{"sql":"SELECT \"account_domain_blocks\".* FROM \"account_domain_blocks\" WHERE \"account_domain_blocks\".\"account_id\" = $1","database_type":"postgres"}},{"id":2854289,"event":"return","thread_id":9160,"parent_id":2854288,"elapsed":0.000938008,"elapsed_instrumentation":0.00016484403749927878},{"id":2854290,"event":"call","thread_id":9160,"sql_query":{"sql":"SELECT \"announcement_mutes\".* FROM \"announcement_mutes\" WHERE \"announcement_mutes\".\"account_id\" = $1","database_type":"postgres"}},{"id":2854291,"event":"return","thread_id":9160,"parent_id":2854290,"elapsed":0.000852142,"elapsed_instrumentation":0.0001863660290837288},{"id":2854292,"event":"call","thread_id":9160,"defined_class":"FeedManager","method_id":"clean_feeds!","path":"app/lib/feed_manager.rb","lineno":294,"static":false,"parameters":[{"name":"type","class":"Symbol","object_id":426588,"value":":home","kind":"req"},{"name":"ids","class":"Array","object_id":13981080,"value":"[111361437184298729]","kind":"req","size":1}],"receiver":{"class":"FeedManager","object_id":496900,"value":"#<FeedManager:0x00007fc932f2fde8>"}},{"id":2854293,"event":"call","thread_id":9160,"defined_class":"Redisable","method_id":"redis","path":"app/models/concerns/redisable.rb","lineno":4,"static":false,"parameters":[],"receiver":{"class":"FeedManager","object_id":496900,"value":"#<FeedManager:0x00007fc932f2fde8>"}},{"id":2854294,"event":"return","thread_id":9160,"parent_id":2854293,"elapsed":8.917006198316813e-06,"elapsed_instrumentation":0.0001642869901843369,"return_value":{"class":"Redis::Namespace","value":"#<Redis::Namespace:0x00007fc934c37e90>","object_id":319760}},{"id":2854295,"event":"call","thread_id":9160,"defined_class":"FeedManager","method_id":"key","path":"app/lib/feed_manager.rb","lineno":29,"static":false,"parameters":[{"name":"type","class":"Symbol","object_id":426588,"value":":home","kind":"req"},{"name":"id","class":"Integer","object_id":222722874368597459,"value":"111361437184298729","kind":"req"},{"name":"subtype","class":"String","object_id":497080,"value":"reblogs","kind":"opt"}],"receiver":{"class":"FeedManager","object_id":496900,"value":"#<FeedManager:0x00007fc932f2fde8>"}},{"id":2854296,"event":"return","thread_id":9160,"parent_id":2854295,"elapsed":1.0021030902862549e-05,"elapsed_instrumentation":0.00020211900118738413,"return_value":{"class":"String","value":"feed:home:111361437184298729:reblogs","object_id":13981100}},{"id":2854297,"event":"call","thread_id":9160,"defined_class":"FeedManager","method_id":"key","path":"app/lib/feed_manager.rb","lineno":29,"static":false,"parameters":[{"name":"type","class":"Symbol","object_id":426588,"value":":home","kind":"req"},{"name":"id","class":"Integer","object_id":222722874368597459,"value":"111361437184298729","kind":"req"},{"name":"subtype","class":"NilClass","object_id":4,"value":null,"kind":"opt"}],"receiver":{"class":"FeedManager","object_id":496900,"value":"#<FeedManager:0x00007fc932f2fde8>"}},{"id":2854298,"event":"return","thread_id":9160,"parent_id":2854297,"elapsed":4.243978764861822e-06,"elapsed_instrumentation":0.00011275900760665536,"return_value":{"class":"String","value":"feed:home:111361437184298729","object_id":13981120}},{"id":2854299,"event":"return","thread_id":9160,"parent_id":2854292,"elapsed":0.0020132899517193437,"elapsed_instrumentation":0.00043258199002593756},{"id":2854300,"event":"return","thread_id":9160,"parent_id":2854201,"elapsed":0.08940985199296847,"elapsed_instrumentation":0.00033731997245922685,"return_value":{"class":"Array","value":"[#<Proc:0x00007fc931571348 /workspaces/mastodon/vendor/bundle/ruby/3.2.0/gems/activesupport-7.1.1/lib, #<Proc:0x00007fc931571488 /workspaces/mastodon/vendor/bundle/ruby/3.2.0/gems/activesupport-7.1.1/lib, #<Proc:0x00007fc9315715c8 /workspaces/mastodon/vendor/bundle/ruby/3.2.0/gems/activesupport-7.1.1/lib, #<Proc:0x00007fc931571708 /workspaces/mastodon/vendor/bundle/ruby/3.2.0/gems/activesupport-7.1.1/lib, #<Proc:0x00007fc931571848 /workspaces/mastodon/vendor/bundle/ruby/3.2.0/gems/activesupport-7.1.1/lib, #<Proc:0x00007fc931571988 /workspaces/mastodon/vendor/bundle/ruby/3.2.0/gems/activesupport-7.1.1/lib, #<Proc:0x00007fc931571af0 /workspaces/mastodon/vendor/bundle/ruby/3.2.0/gems/activesupport-7.1.1/lib, #<Proc:0x00007fc931571c30 /workspaces/mastodon/vendor/bundle/ruby/3.2.0/gems/activesupport-7.1.1/lib, #<Proc:0x00007fc931571de8 /workspaces/mastodon/vendor/bundle/ruby/3.2.0/gems/activesupport-7.1.1/lib, #<Proc:0x00007fc931571f78 /workspaces/mastodon/vendor/bundle/ruby/3.2.0/gems/activesupport-7.1.1/lib (...34 more items)]","object_id":5268780,"size":44}},{"id":2854301,"event":"call","thread_id":9160,"sql_query":{"sql":"DELETE FROM \"accounts_tags\" WHERE \"accounts_tags\".\"account_id\" = $1","database_type":"postgres"}},{"id":2854302,"event":"return","thread_id":9160,"parent_id":2854301,"elapsed":0.000898537,"elapsed_instrumentation":0.00012376898666843772},{"id":2854303,"event":"call","thread_id":9160,"sql_query":{"sql":"DELETE FROM \"accounts\" WHERE \"accounts\".\"id\" = $1","database_type":"postgres"}},{"id":2854304,"event":"return","thread_id":9160,"parent_id":2854303,"elapsed":0.007851331,"elapsed_instrumentation":0.00014657701831310987},{"id":2854305,"event":"call","thread_id":9160,"defined_class":"ActiveSupport::Callbacks::CallbackSequence","method_id":"invoke_after","path":"vendor/bundle/ruby/3.2.0/gems/activesupport-7.1.1/lib/active_support/callbacks.rb","lineno":601,"static":false,"parameters":[{"name":"arg","class":"ActiveSupport::Callbacks::Filters::Environment","object_id":13980980,"value":null,"kind":"req"}],"receiver":{"class":"ActiveSupport::Callbacks::CallbackSequence","object_id":5268680,"value":"#<ActiveSupport::Callbacks::CallbackSequence:0x00007fc930d01c30>"}},{"id":2854306,"event":"return","thread_id":9160,"parent_id":2854305,"elapsed":0.0001235100207850337,"elapsed_instrumentation":0.0002609639777801931,"return_value":{"class":"Array","value":"[#<Proc:0x00007fc931571190 /workspaces/mastodon/vendor/bundle/ruby/3.2.0/gems/activesupport-7.1.1/lib]","object_id":5268840,"size":1}},{"id":2854307,"event":"call","thread_id":9160,"sql_query":{"sql":"RELEASE SAVEPOINT active_record_1","database_type":"postgres"}},{"id":2854308,"event":"return","thread_id":9160,"parent_id":2854307,"elapsed":0.000800014,"elapsed_instrumentation":9.300699457526207e-05},{"id":2854309,"event":"call","thread_id":9160,"defined_class":"ActiveSupport::Callbacks::CallbackSequence","method_id":"invoke_before","path":"vendor/bundle/ruby/3.2.0/gems/activesupport-7.1.1/lib/active_support/callbacks.rb","lineno":597,"static":false,"parameters":[{"name":"arg","class":"ActiveSupport::Callbacks::Filters::Environment","object_id":13981140,"value":null,"kind":"req"}],"receiver":{"class":"ActiveSupport::Callbacks::CallbackSequence","object_id":328280,"value":"#<ActiveSupport::Callbacks::CallbackSequence:0x00007fc9378db2d0>"}},{"id":2854310,"event":"return","thread_id":9160,"parent_id":2854309,"elapsed":4.266039468348026e-06,"elapsed_instrumentation":0.00014093396021053195,"return_value":{"class":"Array","value":"[]","object_id":328300,"size":0}},{"id":2854311,"event":"call","thread_id":9160,"defined_class":"ActiveSupport::Callbacks::CallbackSequence","method_id":"invoke_after","path":"vendor/bundle/ruby/3.2.0/gems/activesupport-7.1.1/lib/active_support/callbacks.rb","lineno":601,"static":false,"parameters":[{"name":"arg","class":"ActiveSupport::Callbacks::Filters::Environment","object_id":13981140,"value":null,"kind":"req"}],"receiver":{"class":"ActiveSupport::Callbacks::CallbackSequence","object_id":328280,"value":"#<ActiveSupport::Callbacks::CallbackSequence:0x00007fc9378db2d0>"}},{"id":2854312,"event":"return","thread_id":9160,"parent_id":2854311,"elapsed":0.0001269819913432002,"elapsed_instrumentation":0.0001606559962965548,"return_value":{"class":"Array","value":"[#<Proc:0x00007fc938945850 /workspaces/mastodon/vendor/bundle/ruby/3.2.0/gems/activesupport-7.1.1/lib, #<Proc:0x00007fc938942a10 /workspaces/mastodon/vendor/bundle/ruby/3.2.0/gems/activesupport-7.1.1/lib, #<Proc:0x00007fc93855fba0 /workspaces/mastodon/vendor/bundle/ruby/3.2.0/gems/activesupport-7.1.1/lib, #<Proc:0x00007fc93855f0b0 /workspaces/mastodon/vendor/bundle/ruby/3.2.0/gems/activesupport-7.1.1/lib, #<Proc:0x00007fc93855ebb0 /workspaces/mastodon/vendor/bundle/ruby/3.2.0/gems/activesupport-7.1.1/lib, #<Proc:0x00007fc93855de40 /workspaces/mastodon/vendor/bundle/ruby/3.2.0/gems/activesupport-7.1.1/lib]","object_id":328320,"size":6}},{"id":2854313,"event":"call","thread_id":9160,"defined_class":"Account","method_id":"bot","path":"app/models/account.rb","lineno":171,"static":false,"parameters":[],"receiver":{"class":"Account","object_id":13981160,"value":"#<Account:0x00007fc8e21d2588>"}},{"id":2854314,"event":"return","thread_id":9160,"parent_id":2854313,"elapsed":2.7382979169487953e-05,"elapsed_instrumentation":0.00012246903497725725},{"id":2854315,"event":"call","thread_id":9160,"defined_class":"Account","method_id":"group","path":"app/models/account.rb","lineno":185,"static":false,"parameters":[],"receiver":{"class":"Account","object_id":13981160,"value":"#<Account:0x00007fc8e21d2588>"}},{"id":2854316,"event":"return","thread_id":9160,"parent_id":2854315,"elapsed":7.34301283955574e-06,"elapsed_instrumentation":6.218603812158108e-05},{"id":2854317,"event":"call","thread_id":9160,"defined_class":"Account","method_id":"suspended?","path":"app/models/account.rb","lineno":237,"static":false,"parameters":[],"receiver":{"class":"Account","object_id":13981160,"value":"#<Account:0x00007fc8e21d2588>"}},{"id":2854318,"event":"return","thread_id":9160,"parent_id":2854317,"elapsed":2.4104956537485123e-05,"elapsed_instrumentation":5.348597187548876e-05},{"id":2854319,"event":"call","thread_id":9160,"defined_class":"Account","method_id":"silenced?","path":"app/models/account.rb","lineno":225,"static":false,"parameters":[],"receiver":{"class":"Account","object_id":13981160,"value":"#<Account:0x00007fc8e21d2588>"}},{"id":2854320,"event":"return","thread_id":9160,"parent_id":2854319,"elapsed":1.1523021385073662e-05,"elapsed_instrumentation":5.3822004701942205e-05},{"id":2854321,"event":"call","thread_id":9160,"defined_class":"ActiveSupport::Callbacks::CallbackSequence","method_id":"invoke_before","path":"vendor/bundle/ruby/3.2.0/gems/activesupport-7.1.1/lib/active_support/callbacks.rb","lineno":597,"static":false,"parameters":[{"name":"arg","class":"ActiveSupport::Callbacks::Filters::Environment","object_id":13981180,"value":null,"kind":"req"}],"receiver":{"class":"ActiveSupport::Callbacks::CallbackSequence","object_id":5268680,"value":"#<ActiveSupport::Callbacks::CallbackSequence:0x00007fc930d01c30>"}},{"id":2854322,"event":"call","thread_id":9160,"sql_query":{"sql":"SAVEPOINT active_record_1","database_type":"postgres"}},{"id":2854323,"event":"return","thread_id":9160,"parent_id":2854322,"elapsed":0.000434255,"elapsed_instrumentation":8.546101162210107e-05},{"id":2854324,"event":"call","thread_id":9160,"sql_query":{"sql":"SELECT \"users\".\"id\", \"users\".\"email\", \"users\".\"created_at\", \"users\".\"updated_at\", \"users\".\"encrypted_password\", \"users\".\"reset_password_token\", \"users\".\"reset_password_sent_at\", \"users\".\"sign_in_count\", \"users\".\"current_sign_in_at\", \"users\".\"last_sign_in_at\", \"users\".\"admin\", \"users\".\"confirmation_token\", \"users\".\"confirmed_at\", \"users\".\"confirmation_sent_at\", \"users\".\"unconfirmed_email\", \"users\".\"locale\", \"users\".\"encrypted_otp_secret\", \"users\".\"encrypted_otp_secret_iv\", \"users\".\"encrypted_otp_secret_salt\", \"users\".\"consumed_timestep\", \"users\".\"otp_required_for_login\", \"users\".\"last_emailed_at\", \"users\".\"otp_backup_codes\", \"users\".\"account_id\", \"users\".\"disabled\", \"users\".\"moderator\", \"users\".\"invite_id\", \"users\".\"chosen_languages\", \"users\".\"created_by_application_id\", \"users\".\"approved\", \"users\".\"sign_in_token\", \"users\".\"sign_in_token_sent_at\", \"users\".\"webauthn_id\", \"users\".\"sign_up_ip\", \"users\".\"role_id\", \"users\".\"settings\", \"users\".\"time_zone\" FROM \"users\" WHERE \"users\".\"account_id\" = $1 LIMIT $2","database_type":"postgres"}},{"id":2854325,"event":"return","thread_id":9160,"parent_id":2854324,"elapsed":0.000604554,"elapsed_instrumentation":7.837102748453617e-05},{"id":2854326,"event":"call","thread_id":9160,"sql_query":{"sql":"SELECT \"devices\".* FROM \"devices\" WHERE \"devices\".\"account_id\" = $1","database_type":"postgres"}},{"id":2854327,"event":"return","thread_id":9160,"parent_id":2854326,"elapsed":0.000771006,"elapsed_instrumentation":0.00010507297702133656},{"id":2854328,"event":"call","thread_id":9160,"sql_query":{"sql":"SELECT \"statuses\".* FROM \"statuses\" WHERE \"statuses\".\"deleted_at\" IS NULL AND \"statuses\".\"account_id\" = $1 ORDER BY \"statuses\".\"id\" DESC","database_type":"postgres"}},{"id":2854329,"event":"return","thread_id":9160,"parent_id":2854328,"elapsed":0.000521798,"elapsed_instrumentation":0.00010594498598948121},{"id":2854330,"event":"call","thread_id":9160,"sql_query":{"sql":"SELECT \"favourites\".* FROM \"favourites\" WHERE \"favourites\".\"account_id\" = $1","database_type":"postgres"}},{"id":2854331,"event":"return","thread_id":9160,"parent_id":2854330,"elapsed":0.00055255,"elapsed_instrumentation":9.944301564246416e-05},{"id":2854332,"event":"call","thread_id":9160,"sql_query":{"sql":"SELECT \"bookmarks\".* FROM \"bookmarks\" WHERE \"bookmarks\".\"account_id\" = $1","database_type":"postgres"}},{"id":2854333,"event":"return","thread_id":9160,"parent_id":2854332,"elapsed":0.000469422,"elapsed_instrumentation":9.050703374668956e-05},{"id":2854334,"event":"call","thread_id":9160,"sql_query":{"sql":"SELECT \"mentions\".* FROM \"mentions\" WHERE \"mentions\".\"account_id\" = $1","database_type":"postgres"}},{"id":2854335,"event":"return","thread_id":9160,"parent_id":2854334,"elapsed":0.000505758,"elapsed_instrumentation":0.0002348549896851182},{"id":2854336,"event":"call","thread_id":9160,"sql_query":{"sql":"SELECT \"notifications\".* FROM \"notifications\" WHERE \"notifications\".\"account_id\" = $1","database_type":"postgres"}},{"id":2854337,"event":"return","thread_id":9160,"parent_id":2854336,"elapsed":0.0004129,"elapsed_instrumentation":0.00022178597282618284},{"id":2854338,"event":"call","thread_id":9160,"sql_query":{"sql":"SELECT \"account_conversations\".* FROM \"account_conversations\" WHERE \"account_conversations\".\"account_id\" = $1","database_type":"postgres"}},{"id":2854339,"event":"return","thread_id":9160,"parent_id":2854338,"elapsed":0.000486097,"elapsed_instrumentation":8.754996815696359e-05},{"id":2854340,"event":"call","thread_id":9160,"sql_query":{"sql":"SELECT \"scheduled_statuses\".* FROM \"scheduled_statuses\" WHERE \"scheduled_statuses\".\"account_id\" = $1","database_type":"postgres"}},{"id":2854341,"event":"return","thread_id":9160,"parent_id":2854340,"elapsed":0.00050047,"elapsed_instrumentation":8.61379667185247e-05},{"id":2854342,"event":"call","thread_id":9160,"sql_query":{"sql":"SELECT \"status_pins\".* FROM \"status_pins\" WHERE \"status_pins\".\"account_id\" = $1","database_type":"postgres"}},{"id":2854343,"event":"return","thread_id":9160,"parent_id":2854342,"elapsed":0.000393619,"elapsed_instrumentation":7.762998575344682e-05},{"id":2854344,"event":"call","thread_id":9160,"sql_query":{"sql":"SELECT \"account_pins\".* FROM \"account_pins\" WHERE \"account_pins\".\"account_id\" = $1","database_type":"postgres"}},{"id":2854345,"event":"return","thread_id":9160,"parent_id":2854344,"elapsed":0.000450146,"elapsed_instrumentation":7.93730141595006e-05},{"id":2854346,"event":"call","thread_id":9160,"sql_query":{"sql":"SELECT \"media_attachments\".* FROM \"media_attachments\" WHERE \"media_attachments\".\"account_id\" = $1 ORDER BY \"media_attachments\".\"id\" ASC","database_type":"postgres"}},{"id":2854347,"event":"return","thread_id":9160,"parent_id":2854346,"elapsed":0.000487437,"elapsed_instrumentation":7.753400132060051e-05},{"id":2854348,"event":"call","thread_id":9160,"sql_query":{"sql":"SELECT \"polls\".* FROM \"polls\" WHERE \"polls\".\"account_id\" = $1","database_type":"postgres"}},{"id":2854349,"event":"return","thread_id":9160,"parent_id":2854348,"elapsed":0.000402336,"elapsed_instrumentation":7.467396790161729e-05},{"id":2854350,"event":"call","thread_id":9160,"sql_query":{"sql":"SELECT \"reports\".\"id\", \"reports\".\"status_ids\", \"reports\".\"comment\", \"reports\".\"created_at\", \"reports\".\"updated_at\", \"reports\".\"account_id\", \"reports\".\"action_taken_by_account_id\", \"reports\".\"target_account_id\", \"reports\".\"assigned_account_id\", \"reports\".\"uri\", \"reports\".\"forwarded\", \"reports\".\"category\", \"reports\".\"action_taken_at\", \"reports\".\"rule_ids\" FROM \"reports\" WHERE \"reports\".\"account_id\" = $1","database_type":"postgres"}},{"id":2854351,"event":"return","thread_id":9160,"parent_id":2854350,"elapsed":0.000391264,"elapsed_instrumentation":7.550203008577228e-05},{"id":2854352,"event":"call","thread_id":13276700,"defined_class":"RequestPool","method_id":"flush","path":"app/lib/request_pool.rb","lineno":114,"static":false,"parameters":[{"name":"*","class":"Array","object_id":13981200,"value":"[]","kind":"rest","size":0},{"name":"**","class":"Hash","object_id":13981220,"value":"{}","kind":"keyrest","size":0},{"name":"&","class":"NilClass","object_id":4,"value":null,"kind":"block"}],"receiver":{"class":"RequestPool","object_id":13276720,"value":"#<RequestPool:0x00007fc937dbdb90>"}},{"id":2854353,"event":"call","thread_id":13276700,"defined_class":"ConnectionPool::SharedConnectionPool","method_id":"flush","path":"app/lib/connection_pool/shared_connection_pool.rb","lineno":13,"static":false,"parameters":[{"name":"*","class":"Array","object_id":13981240,"value":"[]","kind":"rest","size":0},{"name":"**","class":"Hash","object_id":13981260,"value":"{}","kind":"keyrest","size":0},{"name":"&","class":"NilClass","object_id":4,"value":null,"kind":"block"}],"receiver":{"class":"ConnectionPool::SharedConnectionPool","object_id":13276740,"value":"#<ConnectionPool::SharedConnectionPool:0x00007fc93772a698>"}},{"id":2854354,"event":"call","thread_id":13276700,"defined_class":"ConnectionPool::SharedTimedStack","method_id":"flush","path":"app/lib/connection_pool/shared_timed_stack.rb","lineno":51,"static":false,"parameters":[],"receiver":{"class":"ConnectionPool::SharedTimedStack","object_id":13276780,"value":"#<ConnectionPool::SharedTimedStack:0x00007fc93772a5a8>"}},{"id":2854355,"event":"return","thread_id":13276700,"parent_id":2854354,"elapsed":6.112037226557732e-06,"elapsed_instrumentation":8.036597864702344e-05,"return_value":{"class":"Array","value":"[]","object_id":13277080,"size":0}},{"id":2854356,"event":"return","thread_id":13276700,"parent_id":2854353,"elapsed":0.00012190599227324128,"elapsed_instrumentation":0.0001661580172367394,"return_value":{"class":"Array","value":"[]","object_id":13277080,"size":0}},{"id":2854357,"event":"return","thread_id":13276700,"parent_id":2854352,"elapsed":0.000324664986692369,"elapsed_instrumentation":0.000349146022927016,"return_value":{"class":"Array","value":"[]","object_id":13277080,"size":0}},{"id":2854358,"event":"call","thread_id":9160,"sql_query":{"sql":"SELECT \"reports\".\"id\", \"reports\".\"status_ids\", \"reports\".\"comment\", \"reports\".\"created_at\", \"reports\".\"updated_at\", \"reports\".\"account_id\", \"reports\".\"action_taken_by_account_id\", \"reports\".\"target_account_id\", \"reports\".\"assigned_account_id\", \"reports\".\"uri\", \"reports\".\"forwarded\", \"reports\".\"category\", \"reports\".\"action_taken_at\", \"reports\".\"rule_ids\" FROM \"reports\" WHERE \"reports\".\"target_account_id\" = $1","database_type":"postgres"}},{"id":2854359,"event":"return","thread_id":9160,"parent_id":2854358,"elapsed":0.001099215,"elapsed_instrumentation":7.457297760993242e-05},{"id":2854360,"event":"call","thread_id":9160,"sql_query":{"sql":"SELECT \"report_notes\".* FROM \"report_notes\" WHERE \"report_notes\".\"account_id\" = $1","database_type":"postgres"}},{"id":2854361,"event":"return","thread_id":9160,"parent_id":2854360,"elapsed":0.000499053,"elapsed_instrumentation":0.00011573301162570715},{"id":2854362,"event":"call","thread_id":9160,"sql_query":{"sql":"SELECT \"custom_filters\".\"id\", \"custom_filters\".\"account_id\", \"custom_filters\".\"expires_at\", \"custom_filters\".\"phrase\", \"custom_filters\".\"context\", \"custom_filters\".\"created_at\", \"custom_filters\".\"updated_at\", \"custom_filters\".\"action\" FROM \"custom_filters\" WHERE \"custom_filters\".\"account_id\" = $1","database_type":"postgres"}},{"id":2854363,"event":"return","thread_id":9160,"parent_id":2854362,"elapsed":0.000592682,"elapsed_instrumentation":8.075602818280458e-05},{"id":2854364,"event":"call","thread_id":9160,"sql_query":{"sql":"SELECT \"account_moderation_notes\".* FROM \"account_moderation_notes\" WHERE \"account_moderation_notes\".\"account_id\" = $1","database_type":"postgres"}},{"id":2854365,"event":"return","thread_id":9160,"parent_id":2854364,"elapsed":0.000430867,"elapsed_instrumentation":0.00015956698916852474},{"id":2854366,"event":"call","thread_id":9160,"sql_query":{"sql":"SELECT \"account_moderation_notes\".* FROM \"account_moderation_notes\" WHERE \"account_moderation_notes\".\"target_account_id\" = $1","database_type":"postgres"}},{"id":2854367,"event":"return","thread_id":9160,"parent_id":2854366,"elapsed":0.000632426,"elapsed_instrumentation":7.145700510591269e-05},{"id":2854368,"event":"call","thread_id":9160,"sql_query":{"sql":"SELECT \"account_warnings\".* FROM \"account_warnings\" WHERE \"account_warnings\".\"account_id\" = $1","database_type":"postgres"}},{"id":2854369,"event":"return","thread_id":9160,"parent_id":2854368,"elapsed":0.000347871,"elapsed_instrumentation":0.00015986704966053367},{"id":2854370,"event":"call","thread_id":9160,"sql_query":{"sql":"SELECT \"account_warnings\".* FROM \"account_warnings\" WHERE \"account_warnings\".\"target_account_id\" = $1","database_type":"postgres"}},{"id":2854371,"event":"return","thread_id":9160,"parent_id":2854370,"elapsed":0.000415837,"elapsed_instrumentation":7.535895565524697e-05},{"id":2854372,"event":"call","thread_id":9160,"sql_query":{"sql":"SELECT \"list_accounts\".* FROM \"list_accounts\" WHERE \"list_accounts\".\"account_id\" = $1","database_type":"postgres"}},{"id":2854373,"event":"return","thread_id":9160,"parent_id":2854372,"elapsed":0.000344687,"elapsed_instrumentation":7.51909683458507e-05},{"id":2854374,"event":"call","thread_id":9160,"sql_query":{"sql":"SELECT \"lists\".* FROM \"lists\" WHERE \"lists\".\"account_id\" = $1","database_type":"postgres"}},{"id":2854375,"event":"return","thread_id":9160,"parent_id":2854374,"elapsed":0.000317075,"elapsed_instrumentation":7.298600394278765e-05},{"id":2854376,"event":"call","thread_id":9160,"sql_query":{"sql":"SELECT \"account_migrations\".* FROM \"account_migrations\" WHERE \"account_migrations\".\"account_id\" = $1","database_type":"postgres"}},{"id":2854377,"event":"return","thread_id":9160,"parent_id":2854376,"elapsed":0.000388108,"elapsed_instrumentation":7.281999569386244e-05},{"id":2854378,"event":"call","thread_id":9160,"sql_query":{"sql":"SELECT \"account_aliases\".* FROM \"account_aliases\" WHERE \"account_aliases\".\"account_id\" = $1","database_type":"postgres"}},{"id":2854379,"event":"return","thread_id":9160,"parent_id":2854378,"elapsed":0.000459466,"elapsed_instrumentation":7.53119820728898e-05},{"id":2854380,"event":"call","thread_id":9160,"sql_query":{"sql":"SELECT \"featured_tags\".* FROM \"featured_tags\" WHERE \"featured_tags\".\"account_id\" = $1","database_type":"postgres"}},{"id":2854381,"event":"return","thread_id":9160,"parent_id":2854380,"elapsed":0.00037242,"elapsed_instrumentation":6.649194983765483e-05},{"id":2854382,"event":"call","thread_id":9160,"sql_query":{"sql":"SELECT \"account_deletion_requests\".* FROM \"account_deletion_requests\" WHERE \"account_deletion_requests\".\"account_id\" = $1 LIMIT $2","database_type":"postgres"}},{"id":2854383,"event":"return","thread_id":9160,"parent_id":2854382,"elapsed":0.000299611,"elapsed_instrumentation":6.606796523556113e-05},{"id":2854384,"event":"call","thread_id":9160,"sql_query":{"sql":"SELECT \"follow_recommendation_suppressions\".* FROM \"follow_recommendation_suppressions\" WHERE \"follow_recommendation_suppressions\".\"account_id\" = $1 LIMIT $2","database_type":"postgres"}},{"id":2854385,"event":"return","thread_id":9160,"parent_id":2854384,"elapsed":0.000407038,"elapsed_instrumentation":7.448397809639573e-05},{"id":2854386,"event":"call","thread_id":9160,"sql_query":{"sql":"SELECT \"account_statuses_cleanup_policies\".* FROM \"account_statuses_cleanup_policies\" WHERE \"account_statuses_cleanup_policies\".\"account_id\" = $1 LIMIT $2","database_type":"postgres"}},{"id":2854387,"event":"return","thread_id":9160,"parent_id":2854386,"elapsed":0.000375384,"elapsed_instrumentation":6.661203224211931e-05},{"id":2854388,"event":"call","thread_id":9160,"sql_query":{"sql":"DELETE FROM \"bulk_imports\" WHERE \"bulk_imports\".\"account_id\" = $1","database_type":"postgres"}},{"id":2854389,"event":"return","thread_id":9160,"parent_id":2854388,"elapsed":0.000529241,"elapsed_instrumentation":6.467400817200541e-05},{"id":2854390,"event":"call","thread_id":9160,"sql_query":{"sql":"SELECT \"follow_requests\".* FROM \"follow_requests\" WHERE \"follow_requests\".\"account_id\" = $1","database_type":"postgres"}},{"id":2854391,"event":"return","thread_id":9160,"parent_id":2854390,"elapsed":0.000389467,"elapsed_instrumentation":7.335899863392115e-05},{"id":2854392,"event":"call","thread_id":9160,"sql_query":{"sql":"SELECT \"follows\".* FROM \"follows\" WHERE \"follows\".\"account_id\" = $1","database_type":"postgres"}},{"id":2854393,"event":"return","thread_id":9160,"parent_id":2854392,"elapsed":0.0004232,"elapsed_instrumentation":7.409404497593641e-05},{"id":2854394,"event":"call","thread_id":9160,"sql_query":{"sql":"SELECT \"follows\".* FROM \"follows\" WHERE \"follows\".\"target_account_id\" = $1","database_type":"postgres"}},{"id":2854395,"event":"return","thread_id":9160,"parent_id":2854394,"elapsed":0.000384544,"elapsed_instrumentation":7.304601604118943e-05},{"id":2854396,"event":"call","thread_id":9160,"sql_query":{"sql":"SELECT \"account_notes\".* FROM \"account_notes\" WHERE \"account_notes\".\"account_id\" = $1","database_type":"postgres"}},{"id":2854397,"event":"return","thread_id":9160,"parent_id":2854396,"elapsed":0.000367976,"elapsed_instrumentation":7.520202780142426e-05},{"id":2854398,"event":"call","thread_id":9160,"sql_query":{"sql":"SELECT \"blocks\".* FROM \"blocks\" WHERE \"blocks\".\"account_id\" = $1","database_type":"postgres"}},{"id":2854399,"event":"return","thread_id":9160,"parent_id":2854398,"elapsed":0.00038822,"elapsed_instrumentation":7.606804138049483e-05},{"id":2854400,"event":"call","thread_id":9160,"sql_query":{"sql":"SELECT \"blocks\".* FROM \"blocks\" WHERE \"blocks\".\"target_account_id\" = $1","database_type":"postgres"}},{"id":2854401,"event":"return","thread_id":9160,"parent_id":2854400,"elapsed":0.000390984,"elapsed_instrumentation":7.558299694210291e-05},{"id":2854402,"event":"call","thread_id":9160,"sql_query":{"sql":"SELECT \"mutes\".* FROM \"mutes\" WHERE \"mutes\".\"account_id\" = $1","database_type":"postgres"}},{"id":2854403,"event":"return","thread_id":9160,"parent_id":2854402,"elapsed":0.000372873,"elapsed_instrumentation":7.588200969621539e-05},{"id":2854404,"event":"call","thread_id":9160,"sql_query":{"sql":"SELECT \"mutes\".* FROM \"mutes\" WHERE \"mutes\".\"target_account_id\" = $1","database_type":"postgres"}},{"id":2854405,"event":"return","thread_id":9160,"parent_id":2854404,"elapsed":0.000447408,"elapsed_instrumentation":7.170700700953603e-05},{"id":2854406,"event":"call","thread_id":9160,"sql_query":{"sql":"SELECT \"conversation_mutes\".* FROM \"conversation_mutes\" WHERE \"conversation_mutes\".\"account_id\" = $1","database_type":"postgres"}},{"id":2854407,"event":"return","thread_id":9160,"parent_id":2854406,"elapsed":0.000440833,"elapsed_instrumentation":0.0001958189532160759},{"id":2854408,"event":"call","thread_id":9160,"sql_query":{"sql":"SELECT \"account_domain_blocks\".* FROM \"account_domain_blocks\" WHERE \"account_domain_blocks\".\"account_id\" = $1","database_type":"postgres"}},{"id":2854409,"event":"return","thread_id":9160,"parent_id":2854408,"elapsed":0.000477931,"elapsed_instrumentation":0.00018848699983209372},{"id":2854410,"event":"call","thread_id":9160,"sql_query":{"sql":"SELECT \"announcement_mutes\".* FROM \"announcement_mutes\" WHERE \"announcement_mutes\".\"account_id\" = $1","database_type":"postgres"}},{"id":2854411,"event":"return","thread_id":9160,"parent_id":2854410,"elapsed":0.000393728,"elapsed_instrumentation":7.56240333430469e-05},{"id":2854412,"event":"call","thread_id":9160,"defined_class":"FeedManager","method_id":"clean_feeds!","path":"app/lib/feed_manager.rb","lineno":294,"static":false,"parameters":[{"name":"type","class":"Symbol","object_id":426588,"value":":home","kind":"req"},{"name":"ids","class":"Array","object_id":13981280,"value":"[111361437184298730]","kind":"req","size":1}],"receiver":{"class":"FeedManager","object_id":496900,"value":"#<FeedManager:0x00007fc932f2fde8>"}},{"id":2854413,"event":"call","thread_id":9160,"defined_class":"Redisable","method_id":"redis","path":"app/models/concerns/redisable.rb","lineno":4,"static":false,"parameters":[],"receiver":{"class":"FeedManager","object_id":496900,"value":"#<FeedManager:0x00007fc932f2fde8>"}},{"id":2854414,"event":"return","thread_id":9160,"parent_id":2854413,"elapsed":5.551031790673733e-06,"elapsed_instrumentation":8.779397467151284e-05,"return_value":{"class":"Redis::Namespace","value":"#<Redis::Namespace:0x00007fc934c37e90>","object_id":319760}},{"id":2854415,"event":"call","thread_id":9160,"defined_class":"FeedManager","method_id":"key","path":"app/lib/feed_manager.rb","lineno":29,"static":false,"parameters":[{"name":"type","class":"Symbol","object_id":426588,"value":":home","kind":"req"},{"name":"id","class":"Integer","object_id":222722874368597461,"value":"111361437184298730","kind":"req"},{"name":"subtype","class":"String","object_id":497080,"value":"reblogs","kind":"opt"}],"receiver":{"class":"FeedManager","object_id":496900,"value":"#<FeedManager:0x00007fc932f2fde8>"}},{"id":2854416,"event":"return","thread_id":9160,"parent_id":2854415,"elapsed":7.618044037371874e-06,"elapsed_instrumentation":0.00011770403943955898,"return_value":{"class":"String","value":"feed:home:111361437184298730:reblogs","object_id":13981300}},{"id":2854417,"event":"call","thread_id":9160,"defined_class":"FeedManager","method_id":"key","path":"app/lib/feed_manager.rb","lineno":29,"static":false,"parameters":[{"name":"type","class":"Symbol","object_id":426588,"value":":home","kind":"req"},{"name":"id","class":"Integer","object_id":222722874368597461,"value":"111361437184298730","kind":"req"},{"name":"subtype","class":"NilClass","object_id":4,"value":null,"kind":"opt"}],"receiver":{"class":"FeedManager","object_id":496900,"value":"#<FeedManager:0x00007fc932f2fde8>"}},{"id":2854418,"event":"return","thread_id":9160,"parent_id":2854417,"elapsed":4.8999791033566e-06,"elapsed_instrumentation":0.00020561297424137592,"return_value":{"class":"String","value":"feed:home:111361437184298730","object_id":13981320}},{"id":2854419,"event":"return","thread_id":9160,"parent_id":2854412,"elapsed":0.001059564994648099,"elapsed_instrumentation":0.00018431904027238488},{"id":2854420,"event":"return","thread_id":9160,"parent_id":2854321,"elapsed":0.07185902498895302,"elapsed_instrumentation":0.00022322707809507847,"return_value":{"class":"Array","value":"[#<Proc:0x00007fc931571348 /workspaces/mastodon/vendor/bundle/ruby/3.2.0/gems/activesupport-7.1.1/lib, #<Proc:0x00007fc931571488 /workspaces/mastodon/vendor/bundle/ruby/3.2.0/gems/activesupport-7.1.1/lib, #<Proc:0x00007fc9315715c8 /workspaces/mastodon/vendor/bundle/ruby/3.2.0/gems/activesupport-7.1.1/lib, #<Proc:0x00007fc931571708 /workspaces/mastodon/vendor/bundle/ruby/3.2.0/gems/activesupport-7.1.1/lib, #<Proc:0x00007fc931571848 /workspaces/mastodon/vendor/bundle/ruby/3.2.0/gems/activesupport-7.1.1/lib, #<Proc:0x00007fc931571988 /workspaces/mastodon/vendor/bundle/ruby/3.2.0/gems/activesupport-7.1.1/lib, #<Proc:0x00007fc931571af0 /workspaces/mastodon/vendor/bundle/ruby/3.2.0/gems/activesupport-7.1.1/lib, #<Proc:0x00007fc931571c30 /workspaces/mastodon/vendor/bundle/ruby/3.2.0/gems/activesupport-7.1.1/lib, #<Proc:0x00007fc931571de8 /workspaces/mastodon/vendor/bundle/ruby/3.2.0/gems/activesupport-7.1.1/lib, #<Proc:0x00007fc931571f78 /workspaces/mastodon/vendor/bundle/ruby/3.2.0/gems/activesupport-7.1.1/lib (...34 more items)]","object_id":5268780,"size":44}},{"id":2854421,"event":"call","thread_id":9160,"sql_query":{"sql":"DELETE FROM \"accounts_tags\" WHERE \"accounts_tags\".\"account_id\" = $1","database_type":"postgres"}},{"id":2854422,"event":"return","thread_id":9160,"parent_id":2854421,"elapsed":0.000663434,"elapsed_instrumentation":8.75500263646245e-05},{"id":2854423,"event":"call","thread_id":9160,"sql_query":{"sql":"DELETE FROM \"accounts\" WHERE \"accounts\".\"id\" = $1","database_type":"postgres"}},{"id":2854424,"event":"return","thread_id":9160,"parent_id":2854423,"elapsed":0.005330643,"elapsed_instrumentation":0.00012658897321671247},{"id":2854425,"event":"call","thread_id":9160,"defined_class":"ActiveSupport::Callbacks::CallbackSequence","method_id":"invoke_after","path":"vendor/bundle/ruby/3.2.0/gems/activesupport-7.1.1/lib/active_support/callbacks.rb","lineno":601,"static":false,"parameters":[{"name":"arg","class":"ActiveSupport::Callbacks::Filters::Environment","object_id":13981180,"value":null,"kind":"req"}],"receiver":{"class":"ActiveSupport::Callbacks::CallbackSequence","object_id":5268680,"value":"#<ActiveSupport::Callbacks::CallbackSequence:0x00007fc930d01c30>"}},{"id":2854426,"event":"return","thread_id":9160,"parent_id":2854425,"elapsed":0.00011057301890105009,"elapsed_instrumentation":0.00019283097935840487,"return_value":{"class":"Array","value":"[#<Proc:0x00007fc931571190 /workspaces/mastodon/vendor/bundle/ruby/3.2.0/gems/activesupport-7.1.1/lib]","object_id":5268840,"size":1}},{"id":2854427,"event":"call","thread_id":9160,"sql_query":{"sql":"RELEASE SAVEPOINT active_record_1","database_type":"postgres"}},{"id":2854428,"event":"return","thread_id":9160,"parent_id":2854427,"elapsed":0.000510353,"elapsed_instrumentation":9.542400948703289e-05},{"id":2854429,"event":"call","thread_id":9160,"defined_class":"ActiveSupport::Callbacks::CallbackSequence","method_id":"invoke_before","path":"vendor/bundle/ruby/3.2.0/gems/activesupport-7.1.1/lib/active_support/callbacks.rb","lineno":597,"static":false,"parameters":[{"name":"arg","class":"ActiveSupport::Callbacks::Filters::Environment","object_id":13981340,"value":null,"kind":"req"}],"receiver":{"class":"ActiveSupport::Callbacks::CallbackSequence","object_id":328280,"value":"#<ActiveSupport::Callbacks::CallbackSequence:0x00007fc9378db2d0>"}},{"id":2854430,"event":"return","thread_id":9160,"parent_id":2854429,"elapsed":3.923021722584963e-06,"elapsed_instrumentation":0.00013030203990638256,"return_value":{"class":"Array","value":"[]","object_id":328300,"size":0}},{"id":2854431,"event":"call","thread_id":9160,"defined_class":"ActiveSupport::Callbacks::CallbackSequence","method_id":"invoke_after","path":"vendor/bundle/ruby/3.2.0/gems/activesupport-7.1.1/lib/active_support/callbacks.rb","lineno":601,"static":false,"parameters":[{"name":"arg","class":"ActiveSupport::Callbacks::Filters::Environment","object_id":13981340,"value":null,"kind":"req"}],"receiver":{"class":"ActiveSupport::Callbacks::CallbackSequence","object_id":328280,"value":"#<ActiveSupport::Callbacks::CallbackSequence:0x00007fc9378db2d0>"}},{"id":2854432,"event":"return","thread_id":9160,"parent_id":2854431,"elapsed":0.00010346301132813096,"elapsed_instrumentation":0.0001541969832032919,"return_value":{"class":"Array","value":"[#<Proc:0x00007fc938945850 /workspaces/mastodon/vendor/bundle/ruby/3.2.0/gems/activesupport-7.1.1/lib, #<Proc:0x00007fc938942a10 /workspaces/mastodon/vendor/bundle/ruby/3.2.0/gems/activesupport-7.1.1/lib, #<Proc:0x00007fc93855fba0 /workspaces/mastodon/vendor/bundle/ruby/3.2.0/gems/activesupport-7.1.1/lib, #<Proc:0x00007fc93855f0b0 /workspaces/mastodon/vendor/bundle/ruby/3.2.0/gems/activesupport-7.1.1/lib, #<Proc:0x00007fc93855ebb0 /workspaces/mastodon/vendor/bundle/ruby/3.2.0/gems/activesupport-7.1.1/lib, #<Proc:0x00007fc93855de40 /workspaces/mastodon/vendor/bundle/ruby/3.2.0/gems/activesupport-7.1.1/lib]","object_id":328320,"size":6}},{"id":2854433,"event":"return","thread_id":9160,"parent_id":2854066,"elapsed":0.2873065579915419,"elapsed_instrumentation":0.00017018901417031884,"return_value":{"class":"IO","value":"#<IO:0x00007fc94b108f80>","object_id":195040}},{"id":2854434,"event":"call","thread_id":9160,"sql_query":{"sql":"SELECT 1 AS one FROM \"accounts\" WHERE \"accounts\".\"id\" = $1 LIMIT $2","database_type":"postgres"}},{"id":2854435,"event":"return","thread_id":9160,"parent_id":2854434,"elapsed":0.000615107,"elapsed_instrumentation":7.423799252137542e-05}]}